{
"meta":{"test_sets":[],"test_metrics":[],"learn_metrics":[{"best_value":"Min","name":"RMSE"}],"launch_mode":"Train","parameters":"","iteration_count":1000,"learn_sets":["learn"],"name":"experiment"},
"iterations":[
{"learn":[42639.78829],"iteration":0,"passed_time":12.52355732,"remaining_time":12511.03376},
{"learn":[36469.81254],"iteration":1,"passed_time":25.49152731,"remaining_time":12720.27213},
{"learn":[31183.24065],"iteration":2,"passed_time":38.19897924,"remaining_time":12694.7941},
{"learn":[26860.49349],"iteration":3,"passed_time":50.32241887,"remaining_time":12530.2823},
{"learn":[22924.48256],"iteration":4,"passed_time":50.35538195,"remaining_time":10020.72101},
{"learn":[19990.43112],"iteration":5,"passed_time":54.70404126,"remaining_time":9062.636169},
{"learn":[17657.20204],"iteration":6,"passed_time":67.70166754,"remaining_time":9603.965124},
{"learn":[15728.58851],"iteration":7,"passed_time":80.51713604,"remaining_time":9984.12487},
{"learn":[14240.01868],"iteration":8,"passed_time":93.18615255,"remaining_time":10260.8308},
{"learn":[12980.68473],"iteration":9,"passed_time":105.6222611,"remaining_time":10456.60385},
{"learn":[11830.41669],"iteration":10,"passed_time":118.1717986,"remaining_time":10624.71898},
{"learn":[10950.54658],"iteration":11,"passed_time":130.3467829,"remaining_time":10731.88512},
{"learn":[10182.26906],"iteration":12,"passed_time":142.6642383,"remaining_time":10831.50794},
{"learn":[9564.281989],"iteration":13,"passed_time":155.0852386,"remaining_time":10922.43181},
{"learn":[9098.658175],"iteration":14,"passed_time":167.0928433,"remaining_time":10972.43004},
{"learn":[8649.046228],"iteration":15,"passed_time":178.7404278,"remaining_time":10992.53631},
{"learn":[8307.718758],"iteration":16,"passed_time":191.7374853,"remaining_time":11086.93812},
{"learn":[8011.897804],"iteration":17,"passed_time":204.3731727,"remaining_time":11149.69198},
{"learn":[7659.69526],"iteration":18,"passed_time":216.2827827,"remaining_time":11167.02157},
{"learn":[7357.520193],"iteration":19,"passed_time":228.8276162,"remaining_time":11212.55319},
{"learn":[7053.726875],"iteration":20,"passed_time":241.4515714,"remaining_time":11256.2423},
{"learn":[6745.77702],"iteration":21,"passed_time":253.4177922,"remaining_time":11265.57276},
{"learn":[6545.307792],"iteration":22,"passed_time":266.2334625,"remaining_time":11309.13447},
{"learn":[6313.861905],"iteration":23,"passed_time":278.5615633,"remaining_time":11328.17024},
{"learn":[6127.781828],"iteration":24,"passed_time":291.0925824,"remaining_time":11352.61072},
{"learn":[5939.322725],"iteration":25,"passed_time":303.5695538,"remaining_time":11372.18252},
{"learn":[5781.826454],"iteration":26,"passed_time":315.9877765,"remaining_time":11387.26321},
{"learn":[5648.827299],"iteration":27,"passed_time":328.2154184,"remaining_time":11393.76381},
{"learn":[5525.481943],"iteration":28,"passed_time":340.6668652,"remaining_time":11406.46642},
{"learn":[5398.959552],"iteration":29,"passed_time":352.9789665,"remaining_time":11412.98658},
{"learn":[5303.195925],"iteration":30,"passed_time":365.3651882,"remaining_time":11420.60862},
{"learn":[5180.853841],"iteration":31,"passed_time":377.3747343,"remaining_time":11415.58571},
{"learn":[5073.009182],"iteration":32,"passed_time":389.5729775,"remaining_time":11415.66876},
{"learn":[4965.094839],"iteration":33,"passed_time":402.5140947,"remaining_time":11436.13575},
{"learn":[4840.92153],"iteration":34,"passed_time":414.1768573,"remaining_time":11419.44764},
{"learn":[4794.861458],"iteration":35,"passed_time":415.0338284,"remaining_time":11113.68363},
{"learn":[4691.121306],"iteration":36,"passed_time":428.0518703,"remaining_time":11140.9176},
{"learn":[4616.614129],"iteration":37,"passed_time":440.5234488,"remaining_time":11152.19889},
{"learn":[4535.454842],"iteration":38,"passed_time":452.9743426,"remaining_time":11161.75239},
{"learn":[4463.6604],"iteration":39,"passed_time":465.4794933,"remaining_time":11171.50784},
{"learn":[4410.424149],"iteration":40,"passed_time":477.8989063,"remaining_time":11178.17198},
{"learn":[4363.170845],"iteration":41,"passed_time":490.1923051,"remaining_time":11181.05306},
{"learn":[4282.472646],"iteration":42,"passed_time":502.6706013,"remaining_time":11187.34338},
{"learn":[4214.454853],"iteration":43,"passed_time":515.2558302,"remaining_time":11195.10395},
{"learn":[4141.393689],"iteration":44,"passed_time":527.0679495,"remaining_time":11185.55315},
{"learn":[4081.185332],"iteration":45,"passed_time":539.9139042,"remaining_time":11197.34488},
{"learn":[3996.154001],"iteration":46,"passed_time":552.5654092,"remaining_time":11204.14543},
{"learn":[3924.431948],"iteration":47,"passed_time":564.7934988,"remaining_time":11201.73773},
{"learn":[3860.139338],"iteration":48,"passed_time":577.3682562,"remaining_time":11205.65738},
{"learn":[3796.765457],"iteration":49,"passed_time":589.0953501,"remaining_time":11192.81165},
{"learn":[3712.918346],"iteration":50,"passed_time":602.0163873,"remaining_time":11202.2265},
{"learn":[3619.216953],"iteration":51,"passed_time":613.8155979,"remaining_time":11190.33052},
{"learn":[3565.340357],"iteration":52,"passed_time":626.3404513,"remaining_time":11191.40391},
{"learn":[3519.205888],"iteration":53,"passed_time":638.9321198,"remaining_time":11193.14417},
{"learn":[3454.383819],"iteration":54,"passed_time":651.5645918,"remaining_time":11195.06435},
{"learn":[3393.816136],"iteration":55,"passed_time":663.927947,"remaining_time":11191.92825},
{"learn":[3325.495157],"iteration":56,"passed_time":676.4517595,"remaining_time":11191.12297},
{"learn":[3274.804537],"iteration":57,"passed_time":689.0183181,"remaining_time":11190.60786},
{"learn":[3217.470759],"iteration":58,"passed_time":701.9078894,"remaining_time":11194.836},
{"learn":[3154.463928],"iteration":59,"passed_time":714.3282276,"remaining_time":11191.14223},
{"learn":[3096.449626],"iteration":60,"passed_time":726.7555262,"remaining_time":11187.26949},
{"learn":[3035.257009],"iteration":61,"passed_time":738.9448504,"remaining_time":11179.52048},
{"learn":[2979.674502],"iteration":62,"passed_time":751.3959766,"remaining_time":11175.52429},
{"learn":[2917.346439],"iteration":63,"passed_time":764.0820795,"remaining_time":11174.70041},
{"learn":[2875.680187],"iteration":64,"passed_time":776.8607347,"remaining_time":11174.84288},
{"learn":[2844.044705],"iteration":65,"passed_time":788.7404512,"remaining_time":11161.87245},
{"learn":[2800.704801],"iteration":66,"passed_time":801.1133228,"remaining_time":11155.80194},
{"learn":[2742.50142],"iteration":67,"passed_time":813.4313351,"remaining_time":11148.79418},
{"learn":[2710.681141],"iteration":68,"passed_time":826.4287812,"remaining_time":11150.79993},
{"learn":[2652.835648],"iteration":69,"passed_time":839.1394123,"remaining_time":11148.56648},
{"learn":[2622.328599],"iteration":70,"passed_time":851.9051856,"remaining_time":11146.7594},
{"learn":[2593.153335],"iteration":71,"passed_time":864.2530375,"remaining_time":11139.26137},
{"learn":[2545.552713],"iteration":72,"passed_time":876.8010556,"remaining_time":11134.17231},
{"learn":[2486.152015],"iteration":73,"passed_time":890.0903245,"remaining_time":11138.1573},
{"learn":[2459.896118],"iteration":74,"passed_time":902.490109,"remaining_time":11130.71134},
{"learn":[2436.133792],"iteration":75,"passed_time":914.9326557,"remaining_time":11123.65492},
{"learn":[2403.094413],"iteration":76,"passed_time":927.3339206,"remaining_time":11115.96375},
{"learn":[2355.492317],"iteration":77,"passed_time":939.5949115,"remaining_time":11106.4937},
{"learn":[2349.175922],"iteration":78,"passed_time":951.9293833,"remaining_time":11097.80965},
{"learn":[2309.875539],"iteration":79,"passed_time":965.1547855,"remaining_time":11099.28003},
{"learn":[2292.816547],"iteration":80,"passed_time":977.5285891,"remaining_time":11090.7256},
{"learn":[2263.230142],"iteration":81,"passed_time":990.950473,"remaining_time":11093.81139},
{"learn":[2231.197635],"iteration":82,"passed_time":1003.575598,"remaining_time":11087.69667},
{"learn":[2218.522931],"iteration":83,"passed_time":1015.996862,"remaining_time":11079.20388},
{"learn":[2181.317791],"iteration":84,"passed_time":1028.433494,"remaining_time":11070.78408},
{"learn":[2142.224788],"iteration":85,"passed_time":1040.882211,"remaining_time":11062.39932},
{"learn":[2134.858577],"iteration":86,"passed_time":1052.987413,"remaining_time":11050.31618},
{"learn":[2111.089457],"iteration":87,"passed_time":1066.175807,"remaining_time":11049.45836},
{"learn":[2090.124568],"iteration":88,"passed_time":1078.352535,"remaining_time":11037.96808},
{"learn":[2059.162144],"iteration":89,"passed_time":1090.857364,"remaining_time":11029.78002},
{"learn":[2023.580887],"iteration":90,"passed_time":1104.858037,"remaining_time":11036.43907},
{"learn":[2016.183986],"iteration":91,"passed_time":1117.392139,"remaining_time":11028.17459},
{"learn":[1974.056602],"iteration":92,"passed_time":1129.298644,"remaining_time":11013.69753},
{"learn":[1941.429758],"iteration":93,"passed_time":1141.782416,"remaining_time":11004.83903},
{"learn":[1930.507125],"iteration":94,"passed_time":1154.451198,"remaining_time":10997.66667},
{"learn":[1914.526232],"iteration":95,"passed_time":1167.613814,"remaining_time":10995.03008},
{"learn":[1901.303429],"iteration":96,"passed_time":1179.428539,"remaining_time":10979.62856},
{"learn":[1878.018987],"iteration":97,"passed_time":1192.375691,"remaining_time":10974.7232},
{"learn":[1845.442282],"iteration":98,"passed_time":1204.925889,"remaining_time":10966.04268},
{"learn":[1818.846988],"iteration":99,"passed_time":1217.059805,"remaining_time":10953.53825},
{"learn":[1797.732373],"iteration":100,"passed_time":1229.184376,"remaining_time":10940.95796},
{"learn":[1767.21969],"iteration":101,"passed_time":1241.426276,"remaining_time":10929.41957},
{"learn":[1738.383838],"iteration":102,"passed_time":1254.16325,"remaining_time":10922.17898},
{"learn":[1716.65041],"iteration":103,"passed_time":1266.678129,"remaining_time":10912.91926},
{"learn":[1685.392849],"iteration":104,"passed_time":1279.128748,"remaining_time":10903.0498},
{"learn":[1661.580934],"iteration":105,"passed_time":1291.491019,"remaining_time":10892.38651},
{"learn":[1649.977889],"iteration":106,"passed_time":1304.005095,"remaining_time":10882.95841},
{"learn":[1637.596657],"iteration":107,"passed_time":1315.921978,"remaining_time":10868.54078},
{"learn":[1607.696694],"iteration":108,"passed_time":1328.514645,"remaining_time":10859.6931},
{"learn":[1597.363021],"iteration":109,"passed_time":1340.436162,"remaining_time":10845.34713},
{"learn":[1578.358835],"iteration":110,"passed_time":1352.420352,"remaining_time":10831.54678},
{"learn":[1551.648547],"iteration":111,"passed_time":1365.179451,"remaining_time":10823.92279},
{"learn":[1530.990826],"iteration":112,"passed_time":1378.333259,"remaining_time":10819.3062},
{"learn":[1517.163343],"iteration":113,"passed_time":1390.768366,"remaining_time":10808.95414},
{"learn":[1490.439366],"iteration":114,"passed_time":1403.246411,"remaining_time":10798.89629},
{"learn":[1460.866735],"iteration":115,"passed_time":1415.656609,"remaining_time":10788.27968},
{"learn":[1438.301588],"iteration":116,"passed_time":1427.694642,"remaining_time":10774.82367},
{"learn":[1434.771539],"iteration":117,"passed_time":1433.310856,"remaining_time":10713.39132},
{"learn":[1410.979626],"iteration":118,"passed_time":1446.155095,"remaining_time":10706.40873},
{"learn":[1400.058052],"iteration":119,"passed_time":1458.636778,"remaining_time":10696.66971},
{"learn":[1378.854991],"iteration":120,"passed_time":1471.09148,"remaining_time":10686.68935},
{"learn":[1357.104752],"iteration":121,"passed_time":1483.54397,"remaining_time":10676.65251},
{"learn":[1332.933686],"iteration":122,"passed_time":1495.984714,"remaining_time":10666.49264},
{"learn":[1320.061293],"iteration":123,"passed_time":1507.55791,"remaining_time":10650.16717},
{"learn":[1310.798318],"iteration":124,"passed_time":1520.347931,"remaining_time":10642.43552},
{"learn":[1288.057656],"iteration":125,"passed_time":1533.255266,"remaining_time":10635.43732},
{"learn":[1278.118504],"iteration":126,"passed_time":1545.155114,"remaining_time":10621.42058},
{"learn":[1259.842871],"iteration":127,"passed_time":1557.159435,"remaining_time":10608.14865},
{"learn":[1247.433469],"iteration":128,"passed_time":1569.655344,"remaining_time":10598.21554},
{"learn":[1228.493479],"iteration":129,"passed_time":1581.688805,"remaining_time":10585.14816},
{"learn":[1218.466412],"iteration":130,"passed_time":1594.295187,"remaining_time":10575.89708},
{"learn":[1205.229589],"iteration":131,"passed_time":1607.074255,"remaining_time":10567.73071},
{"learn":[1185.638761],"iteration":132,"passed_time":1619.306528,"remaining_time":10555.93052},
{"learn":[1172.162522],"iteration":133,"passed_time":1631.90981,"remaining_time":10546.52161},
{"learn":[1157.520542],"iteration":134,"passed_time":1644.376898,"remaining_time":10536.19272},
{"learn":[1139.470975],"iteration":135,"passed_time":1656.592807,"remaining_time":10524.23666},
{"learn":[1127.570111],"iteration":136,"passed_time":1668.940863,"remaining_time":10513.10923},
{"learn":[1110.861953],"iteration":137,"passed_time":1681.576595,"remaining_time":10503.76105},
{"learn":[1097.992168],"iteration":138,"passed_time":1694.176606,"remaining_time":10494.1443},
{"learn":[1094.39787],"iteration":139,"passed_time":1700.375835,"remaining_time":10445.16584},
{"learn":[1077.970926],"iteration":140,"passed_time":1712.772886,"remaining_time":10434.55255},
{"learn":[1061.922282],"iteration":141,"passed_time":1725.63244,"remaining_time":10426.70869},
{"learn":[1052.711449],"iteration":142,"passed_time":1738.908536,"remaining_time":10421.29102},
{"learn":[1037.424606],"iteration":143,"passed_time":1751.636414,"remaining_time":10412.50535},
{"learn":[1020.627185],"iteration":144,"passed_time":1764.835879,"remaining_time":10406.44605},
{"learn":[1006.9344],"iteration":145,"passed_time":1778.266182,"remaining_time":10401.63917},
{"learn":[1000.213269],"iteration":146,"passed_time":1790.648161,"remaining_time":10390.63185},
{"learn":[987.7548255],"iteration":147,"passed_time":1803.785447,"remaining_time":10383.95406},
{"learn":[975.8320462],"iteration":148,"passed_time":1816.911716,"remaining_time":10377.12665},
{"learn":[963.0501562],"iteration":149,"passed_time":1829.701127,"remaining_time":10368.30639},
{"learn":[953.5670763],"iteration":150,"passed_time":1842.2523,"remaining_time":10358.09406},
{"learn":[939.8643931],"iteration":151,"passed_time":1854.867313,"remaining_time":10348.20712},
{"learn":[927.4190361],"iteration":152,"passed_time":1867.441424,"remaining_time":10338.05808},
{"learn":[914.2713891],"iteration":153,"passed_time":1880.152215,"remaining_time":10328.6284},
{"learn":[903.2665226],"iteration":154,"passed_time":1893.596215,"remaining_time":10323.15356},
{"learn":[897.5233732],"iteration":155,"passed_time":1906.67007,"remaining_time":10315.57397},
{"learn":[889.5362276],"iteration":156,"passed_time":1919.373892,"remaining_time":10305.93752},
{"learn":[878.0873697],"iteration":157,"passed_time":1932.10859,"remaining_time":10296.42679},
{"learn":[862.8969222],"iteration":158,"passed_time":1944.619738,"remaining_time":10285.69308},
{"learn":[859.8785663],"iteration":159,"passed_time":1957.18487,"remaining_time":10275.22057},
{"learn":[846.4331122],"iteration":160,"passed_time":1970.795369,"remaining_time":10270.16965},
{"learn":[832.9713044],"iteration":161,"passed_time":1983.424021,"remaining_time":10259.93413},
{"learn":[824.8013399],"iteration":162,"passed_time":1996.207823,"remaining_time":10250.46594},
{"learn":[818.9653826],"iteration":163,"passed_time":2008.600969,"remaining_time":10238.96592},
{"learn":[811.0435961],"iteration":164,"passed_time":2020.606089,"remaining_time":10225.49142},
{"learn":[800.3026957],"iteration":165,"passed_time":2032.255484,"remaining_time":10210.24743},
{"learn":[794.9771836],"iteration":166,"passed_time":2044.983837,"remaining_time":10200.42836},
{"learn":[791.7321482],"iteration":167,"passed_time":2057.310969,"remaining_time":10188.58766},
{"learn":[778.7103345],"iteration":168,"passed_time":2069.556757,"remaining_time":10176.34121},
{"learn":[767.1300856],"iteration":169,"passed_time":2082.033071,"remaining_time":10165.22029},
{"learn":[760.1696121],"iteration":170,"passed_time":2094.411648,"remaining_time":10153.60968},
{"learn":[754.5000228],"iteration":171,"passed_time":2106.835507,"remaining_time":10142.20814},
{"learn":[749.562404],"iteration":172,"passed_time":2118.355249,"remaining_time":10126.47278},
{"learn":[744.0291955],"iteration":173,"passed_time":2130.855752,"remaining_time":10115.44168},
{"learn":[735.3582305],"iteration":174,"passed_time":2143.625719,"remaining_time":10105.6641},
{"learn":[728.5409075],"iteration":175,"passed_time":2155.598313,"remaining_time":10092.11937},
{"learn":[719.0651974],"iteration":176,"passed_time":2168.482452,"remaining_time":10082.83084},
{"learn":[711.6110304],"iteration":177,"passed_time":2180.641886,"remaining_time":10070.15523},
{"learn":[703.8000169],"iteration":178,"passed_time":2193.642711,"remaining_time":10061.3445},
{"learn":[699.6225112],"iteration":179,"passed_time":2205.418447,"remaining_time":10046.90626},
{"learn":[691.6320002],"iteration":180,"passed_time":2217.581199,"remaining_time":10034.24863},
{"learn":[679.4731606],"iteration":181,"passed_time":2229.801375,"remaining_time":10021.85453},
{"learn":[675.9129569],"iteration":182,"passed_time":2242.290192,"remaining_time":10010.66167},
{"learn":[671.0818184],"iteration":183,"passed_time":2254.676405,"remaining_time":9998.999709},
{"learn":[661.2547887],"iteration":184,"passed_time":2267.127939,"remaining_time":9987.617677},
{"learn":[654.942148],"iteration":185,"passed_time":2279.308768,"remaining_time":9975.039449},
{"learn":[646.1027986],"iteration":186,"passed_time":2291.681862,"remaining_time":9963.301358},
{"learn":[642.3394862],"iteration":187,"passed_time":2303.610417,"remaining_time":9949.636481},
{"learn":[638.7497424],"iteration":188,"passed_time":2315.88985,"remaining_time":9937.495601},
{"learn":[630.6276053],"iteration":189,"passed_time":2328.514951,"remaining_time":9926.826897},
{"learn":[622.9651488],"iteration":190,"passed_time":2341.441795,"remaining_time":9917.415772},
{"learn":[621.9190716],"iteration":191,"passed_time":2353.218707,"remaining_time":9903.128726},
{"learn":[611.3318232],"iteration":192,"passed_time":2365.332109,"remaining_time":9890.274674},
{"learn":[605.6966768],"iteration":193,"passed_time":2377.837298,"remaining_time":9879.055989},
{"learn":[600.9780276],"iteration":194,"passed_time":2390.59554,"remaining_time":9868.868766},
{"learn":[593.3284439],"iteration":195,"passed_time":2402.455816,"remaining_time":9854.971818},
{"learn":[590.6113747],"iteration":196,"passed_time":2416.247035,"remaining_time":9848.966341},
{"learn":[586.0940463],"iteration":197,"passed_time":2428.560086,"remaining_time":9836.894895},
{"learn":[583.8880724],"iteration":198,"passed_time":2441.281772,"remaining_time":9826.465824},
{"learn":[576.9713553],"iteration":199,"passed_time":2454.809917,"remaining_time":9819.239667},
{"learn":[569.9786405],"iteration":200,"passed_time":2467.641665,"remaining_time":9809.182539},
{"learn":[562.3155061],"iteration":201,"passed_time":2480.043439,"remaining_time":9797.399328},
{"learn":[556.6092218],"iteration":202,"passed_time":2492.629581,"remaining_time":9786.333873},
{"learn":[550.5915835],"iteration":203,"passed_time":2505.742625,"remaining_time":9777.309459},
{"learn":[548.0789246],"iteration":204,"passed_time":2518.571813,"remaining_time":9767.14435},
{"learn":[540.8469701],"iteration":205,"passed_time":2530.657523,"remaining_time":9754.087733},
{"learn":[536.607324],"iteration":206,"passed_time":2543.582557,"remaining_time":9744.255881},
{"learn":[530.8480387],"iteration":207,"passed_time":2555.980191,"remaining_time":9732.386111},
{"learn":[527.8406156],"iteration":208,"passed_time":2568.445861,"remaining_time":9720.768785},
{"learn":[522.2910241],"iteration":209,"passed_time":2581.010313,"remaining_time":9709.514987},
{"learn":[516.8325257],"iteration":210,"passed_time":2593.621699,"remaining_time":9698.424269},
{"learn":[508.0385876],"iteration":211,"passed_time":2605.919257,"remaining_time":9686.152708},
{"learn":[504.3044348],"iteration":212,"passed_time":2618.588689,"remaining_time":9675.254923},
{"learn":[502.3010573],"iteration":213,"passed_time":2632.316546,"remaining_time":9668.228062},
{"learn":[494.0667098],"iteration":214,"passed_time":2646.178709,"remaining_time":9661.629238},
{"learn":[488.7093627],"iteration":215,"passed_time":2658.7614,"remaining_time":9650.319156},
{"learn":[485.672073],"iteration":216,"passed_time":2670.882082,"remaining_time":9637.330279},
{"learn":[479.519176],"iteration":217,"passed_time":2683.08644,"remaining_time":9624.649525},
{"learn":[479.4392316],"iteration":218,"passed_time":2683.091864,"remaining_time":9568.469159},
{"learn":[473.8479154],"iteration":219,"passed_time":2695.30722,"remaining_time":9556.089235},
{"learn":[469.9690737],"iteration":220,"passed_time":2708.051084,"remaining_time":9545.573729},
{"learn":[464.4190926],"iteration":221,"passed_time":2720.125992,"remaining_time":9532.69379},
{"learn":[464.3531559],"iteration":222,"passed_time":2720.143448,"remaining_time":9477.809234},
{"learn":[455.1831522],"iteration":223,"passed_time":2732.489349,"remaining_time":9466.123818},
{"learn":[451.9083372],"iteration":224,"passed_time":2744.841311,"remaining_time":9454.453406},
{"learn":[448.2178524],"iteration":225,"passed_time":2757.666104,"remaining_time":9444.396303},
{"learn":[444.7420813],"iteration":226,"passed_time":2770.430877,"remaining_time":9434.110431},
{"learn":[440.4945841],"iteration":227,"passed_time":2783.033485,"remaining_time":9423.25373},
{"learn":[433.7362911],"iteration":228,"passed_time":2796.239893,"remaining_time":9414.414662},
{"learn":[432.77826],"iteration":229,"passed_time":2797.068304,"remaining_time":9364.098236},
{"learn":[429.1441683],"iteration":230,"passed_time":2810.070578,"remaining_time":9354.73712},
{"learn":[422.4505791],"iteration":231,"passed_time":2821.901796,"remaining_time":9341.468013},
{"learn":[419.4626259],"iteration":232,"passed_time":2834.158704,"remaining_time":9329.612558},
{"learn":[412.3823093],"iteration":233,"passed_time":2846.566753,"remaining_time":9318.248432},
{"learn":[406.8347938],"iteration":234,"passed_time":2858.595341,"remaining_time":9305.640152},
{"learn":[405.8394472],"iteration":235,"passed_time":2860.290398,"remaining_time":9259.584171},
{"learn":[403.3578338],"iteration":236,"passed_time":2873.008669,"remaining_time":9249.39078},
{"learn":[398.1782727],"iteration":237,"passed_time":2885.364997,"remaining_time":9238.017345},
{"learn":[395.3947285],"iteration":238,"passed_time":2898.278994,"remaining_time":9228.411358},
{"learn":[394.7773337],"iteration":239,"passed_time":2910.902878,"remaining_time":9217.859114},
{"learn":[388.7945965],"iteration":240,"passed_time":2923.219907,"remaining_time":9206.323275},
{"learn":[382.3720226],"iteration":241,"passed_time":2935.524219,"remaining_time":9194.741148},
{"learn":[379.562898],"iteration":242,"passed_time":2947.94231,"remaining_time":9183.507524},
{"learn":[374.7603013],"iteration":243,"passed_time":2960.840739,"remaining_time":9173.752452},
{"learn":[372.36911],"iteration":244,"passed_time":2973.068428,"remaining_time":9161.904748},
{"learn":[367.5362806],"iteration":245,"passed_time":2986.161458,"remaining_time":9152.706259},
{"learn":[364.0036053],"iteration":246,"passed_time":2998.828641,"remaining_time":9142.178002},
{"learn":[361.8784283],"iteration":247,"passed_time":3011.776543,"remaining_time":9132.48371},
{"learn":[359.3161599],"iteration":248,"passed_time":3024.918131,"remaining_time":9123.347454},
{"learn":[355.9911579],"iteration":249,"passed_time":3039.309948,"remaining_time":9117.929843},
{"learn":[350.4337149],"iteration":250,"passed_time":3052.299993,"remaining_time":9108.257749},
{"learn":[345.51544],"iteration":251,"passed_time":3063.180182,"remaining_time":9092.296732},
{"learn":[343.4141964],"iteration":252,"passed_time":3075.205842,"remaining_time":9079.75796},
{"learn":[337.6716029],"iteration":253,"passed_time":3086.186941,"remaining_time":9064.155348},
{"learn":[334.1220196],"iteration":254,"passed_time":3098.298161,"remaining_time":9051.890706},
{"learn":[332.9019529],"iteration":255,"passed_time":3110.779678,"remaining_time":9040.703439},
{"learn":[331.5017875],"iteration":256,"passed_time":3122.828711,"remaining_time":9028.255769},
{"learn":[327.0642623],"iteration":257,"passed_time":3135.224454,"remaining_time":9016.808312},
{"learn":[325.6266724],"iteration":258,"passed_time":3147.795814,"remaining_time":9005.855979},
{"learn":[323.2543547],"iteration":259,"passed_time":3160.913837,"remaining_time":8996.447074},
{"learn":[320.6999108],"iteration":260,"passed_time":3173.119882,"remaining_time":8984.427559},
{"learn":[320.3875775],"iteration":261,"passed_time":3174.55013,"remaining_time":8942.05342},
{"learn":[315.5390208],"iteration":262,"passed_time":3188.040591,"remaining_time":8933.786752},
{"learn":[311.6951567],"iteration":263,"passed_time":3200.638222,"remaining_time":8922.991406},
{"learn":[308.1964186],"iteration":264,"passed_time":3213.319722,"remaining_time":8912.415079},
{"learn":[305.2032001],"iteration":265,"passed_time":3226.067573,"remaining_time":8902.006011},
{"learn":[302.184604],"iteration":266,"passed_time":3238.197567,"remaining_time":8889.88321},
{"learn":[299.5215166],"iteration":267,"passed_time":3250.583638,"remaining_time":8878.459789},
{"learn":[298.9918155],"iteration":268,"passed_time":3253.865946,"remaining_time":8842.289987},
{"learn":[296.0937845],"iteration":269,"passed_time":3266.835396,"remaining_time":8832.554959},
{"learn":[294.3302665],"iteration":270,"passed_time":3278.513204,"remaining_time":8819.321498},
{"learn":[294.2812231],"iteration":271,"passed_time":3278.662889,"remaining_time":8775.244792},
{"learn":[293.0293485],"iteration":272,"passed_time":3291.350078,"remaining_time":8764.877314},
{"learn":[291.6021544],"iteration":273,"passed_time":3303.551641,"remaining_time":8753.206173},
{"learn":[287.2214005],"iteration":274,"passed_time":3316.52554,"remaining_time":8743.567333},
{"learn":[285.5667059],"iteration":275,"passed_time":3328.622716,"remaining_time":8731.604515},
{"learn":[283.7581462],"iteration":276,"passed_time":3341.158847,"remaining_time":8720.78645},
{"learn":[279.2951947],"iteration":277,"passed_time":3353.67348,"remaining_time":8709.900188},
{"learn":[279.2331528],"iteration":278,"passed_time":3354.046966,"remaining_time":8667.626747},
{"learn":[277.1540845],"iteration":279,"passed_time":3366.499279,"remaining_time":8656.712432},
{"learn":[273.8851722],"iteration":280,"passed_time":3378.691131,"remaining_time":8645.120724},
{"learn":[272.2384025],"iteration":281,"passed_time":3392.25139,"remaining_time":8637.008859},
{"learn":[269.3021375],"iteration":282,"passed_time":3403.862046,"remaining_time":8623.919035},
{"learn":[268.5246815],"iteration":283,"passed_time":3417.305376,"remaining_time":8615.460033},
{"learn":[265.4296146],"iteration":284,"passed_time":3430.329419,"remaining_time":8605.914156},
{"learn":[261.1944093],"iteration":285,"passed_time":3442.250927,"remaining_time":8593.591474},
{"learn":[259.5458398],"iteration":286,"passed_time":3455.117588,"remaining_time":8583.619651},
{"learn":[257.328293],"iteration":287,"passed_time":3466.944367,"remaining_time":8571.056907},
{"learn":[253.7991471],"iteration":288,"passed_time":3478.704416,"remaining_time":8558.335087},
{"learn":[249.9558902],"iteration":289,"passed_time":3491.030601,"remaining_time":8547.005954},
{"learn":[246.8025275],"iteration":290,"passed_time":3503.518034,"remaining_time":8536.06284},
{"learn":[244.9505845],"iteration":291,"passed_time":3515.840712,"remaining_time":8524.70967},
{"learn":[242.8969393],"iteration":292,"passed_time":3528.266911,"remaining_time":8513.599679},
{"learn":[241.0795864],"iteration":293,"passed_time":3540.3566,"remaining_time":8501.672651},
{"learn":[238.3525375],"iteration":294,"passed_time":3552.294484,"remaining_time":8489.381733},
{"learn":[235.6760699],"iteration":295,"passed_time":3565.970823,"remaining_time":8481.227903},
{"learn":[233.7674753],"iteration":296,"passed_time":3578.590733,"remaining_time":8470.536315},
{"learn":[232.2619361],"iteration":297,"passed_time":3591.450834,"remaining_time":8460.397602},
{"learn":[228.7202622],"iteration":298,"passed_time":3603.747283,"remaining_time":8448.919215},
{"learn":[226.0973872],"iteration":299,"passed_time":3616.976713,"remaining_time":8439.61233},
{"learn":[224.5897002],"iteration":300,"passed_time":3629.809875,"remaining_time":8429.359145},
{"learn":[221.4312602],"iteration":301,"passed_time":3642.003104,"remaining_time":8417.609824},
{"learn":[219.9822896],"iteration":302,"passed_time":3654.405292,"remaining_time":8406.338246},
{"learn":[217.3564489],"iteration":303,"passed_time":3666.495385,"remaining_time":8394.344698},
{"learn":[217.2963065],"iteration":304,"passed_time":3667.166466,"remaining_time":8356.330144},
{"learn":[214.5085305],"iteration":305,"passed_time":3680.245124,"remaining_time":8346.699726},
{"learn":[212.2046233],"iteration":306,"passed_time":3692.229503,"remaining_time":8334.576695},
{"learn":[210.8920632],"iteration":307,"passed_time":3704.973399,"remaining_time":8324.161012},
{"learn":[210.1241929],"iteration":308,"passed_time":3717.354761,"remaining_time":8312.919548},
{"learn":[208.1439472],"iteration":309,"passed_time":3729.120617,"remaining_time":8300.300729},
{"learn":[207.1911201],"iteration":310,"passed_time":3741.723094,"remaining_time":8289.540873},
{"learn":[207.1454691],"iteration":311,"passed_time":3742.114939,"remaining_time":8251.843199},
{"learn":[204.8165703],"iteration":312,"passed_time":3754.308884,"remaining_time":8240.288189},
{"learn":[202.9196767],"iteration":313,"passed_time":3766.678977,"remaining_time":8229.113944},
{"learn":[201.406377],"iteration":314,"passed_time":3778.736581,"remaining_time":8217.252566},
{"learn":[200.1921139],"iteration":315,"passed_time":3791.943012,"remaining_time":8207.876647},
{"learn":[200.15848],"iteration":316,"passed_time":3792.096634,"remaining_time":8170.353315},
{"learn":[199.3681366],"iteration":317,"passed_time":3803.770788,"remaining_time":8157.772571},
{"learn":[196.5711105],"iteration":318,"passed_time":3816.580573,"remaining_time":8147.621851},
{"learn":[194.0589595],"iteration":319,"passed_time":3829.530163,"remaining_time":8137.751596},
{"learn":[192.1804165],"iteration":320,"passed_time":3842.238342,"remaining_time":8127.351508},
{"learn":[190.2334127],"iteration":321,"passed_time":3854.629397,"remaining_time":8116.269351},
{"learn":[188.0624201],"iteration":322,"passed_time":3866.63835,"remaining_time":8104.378213},
{"learn":[186.9077975],"iteration":323,"passed_time":3867.445697,"remaining_time":8069.115096},
{"learn":[184.8739001],"iteration":324,"passed_time":3880.434873,"remaining_time":8059.364737},
{"learn":[184.1989068],"iteration":325,"passed_time":3893.11301,"remaining_time":8048.951437},
{"learn":[181.9278751],"iteration":326,"passed_time":3906.222093,"remaining_time":8039.411218},
{"learn":[179.4017182],"iteration":327,"passed_time":3918.57714,"remaining_time":8028.304384},
{"learn":[179.361194],"iteration":328,"passed_time":3918.907126,"remaining_time":7992.664685},
{"learn":[177.0561584],"iteration":329,"passed_time":3930.852827,"remaining_time":7980.822406},
{"learn":[177.0229596],"iteration":330,"passed_time":3931.080818,"remaining_time":7945.296275},
{"learn":[175.7097504],"iteration":331,"passed_time":3943.108329,"remaining_time":7933.723986},
{"learn":[174.1716489],"iteration":332,"passed_time":3956.716908,"remaining_time":7925.315848},
{"learn":[174.1130216],"iteration":333,"passed_time":3956.94905,"remaining_time":7890.203795},
{"learn":[171.8987917],"iteration":334,"passed_time":3969.650063,"remaining_time":7880.051618},
{"learn":[170.3607485],"iteration":335,"passed_time":3981.996903,"remaining_time":7869.184356},
{"learn":[169.5352986],"iteration":336,"passed_time":3994.513455,"remaining_time":7858.642199},
{"learn":[168.3014853],"iteration":337,"passed_time":4006.718754,"remaining_time":7847.478743},
{"learn":[168.2747374],"iteration":338,"passed_time":4006.887483,"remaining_time":7812.839606},
{"learn":[167.9513069],"iteration":339,"passed_time":4019.548036,"remaining_time":7802.652069},
{"learn":[167.1583694],"iteration":340,"passed_time":4032.402648,"remaining_time":7792.825059},
{"learn":[165.4480249],"iteration":341,"passed_time":4045.40534,"remaining_time":7783.265244},
{"learn":[162.0102391],"iteration":342,"passed_time":4057.50308,"remaining_time":7771.951963},
{"learn":[161.9952928],"iteration":343,"passed_time":4057.575178,"remaining_time":7737.701502},
{"learn":[161.6213106],"iteration":344,"passed_time":4070.258158,"remaining_time":7727.591575},
{"learn":[160.6755953],"iteration":345,"passed_time":4082.728854,"remaining_time":7717.065521},
{"learn":[158.4931058],"iteration":346,"passed_time":4094.667029,"remaining_time":7705.526138},
{"learn":[157.7575741],"iteration":347,"passed_time":4107.976875,"remaining_time":7696.554375},
{"learn":[156.8058071],"iteration":348,"passed_time":4121.456695,"remaining_time":7687.87481},
{"learn":[156.4784679],"iteration":349,"passed_time":4134.191161,"remaining_time":7677.783585},
{"learn":[156.1872459],"iteration":350,"passed_time":4146.796499,"remaining_time":7667.438541},
{"learn":[153.9408731],"iteration":351,"passed_time":4158.906082,"remaining_time":7656.168014},
{"learn":[152.6750219],"iteration":352,"passed_time":4171.500301,"remaining_time":7645.781005},
{"learn":[150.1745689],"iteration":353,"passed_time":4182.93402,"remaining_time":7633.263777},
{"learn":[148.696679],"iteration":354,"passed_time":4195.724447,"remaining_time":7623.217657},
{"learn":[147.8097892],"iteration":355,"passed_time":4208.291736,"remaining_time":7612.752467},
{"learn":[146.1805014],"iteration":356,"passed_time":4220.419841,"remaining_time":7601.484476},
{"learn":[144.7193519],"iteration":357,"passed_time":4233.718293,"remaining_time":7592.310458},
{"learn":[143.1598083],"iteration":358,"passed_time":4246.232977,"remaining_time":7581.714034},
{"learn":[142.1174925],"iteration":359,"passed_time":4258.82955,"remaining_time":7571.252534},
{"learn":[140.1050977],"iteration":360,"passed_time":4271.377647,"remaining_time":7560.693398},
{"learn":[139.1106502],"iteration":361,"passed_time":4283.750544,"remaining_time":7549.814495},
{"learn":[137.735989],"iteration":362,"passed_time":4296.180005,"remaining_time":7539.02662},
{"learn":[136.3345961],"iteration":363,"passed_time":4308.533914,"remaining_time":7528.097717},
{"learn":[135.9422636],"iteration":364,"passed_time":4320.983947,"remaining_time":7517.328236},
{"learn":[134.7390821],"iteration":365,"passed_time":4333.373312,"remaining_time":7506.444481},
{"learn":[133.7309027],"iteration":366,"passed_time":4345.883376,"remaining_time":7495.760701},
{"learn":[131.9626465],"iteration":367,"passed_time":4358.938884,"remaining_time":7486.003735},
{"learn":[130.4715754],"iteration":368,"passed_time":4371.501728,"remaining_time":7475.386423},
{"learn":[129.9117805],"iteration":369,"passed_time":4384.033158,"remaining_time":7464.705107},
{"learn":[127.9292524],"iteration":370,"passed_time":4396.419552,"remaining_time":7453.76792},
{"learn":[126.4514544],"iteration":371,"passed_time":4409.285271,"remaining_time":7443.632125},
{"learn":[125.1974127],"iteration":372,"passed_time":4421.921306,"remaining_time":7433.0956},
{"learn":[123.490245],"iteration":373,"passed_time":4433.926263,"remaining_time":7421.491553},
{"learn":[122.8301984],"iteration":374,"passed_time":4446.687759,"remaining_time":7411.146264},
{"learn":[121.6293293],"iteration":375,"passed_time":4458.479726,"remaining_time":7399.179119},
{"learn":[120.5270879],"iteration":376,"passed_time":4470.831535,"remaining_time":7388.138054},
{"learn":[118.9432211],"iteration":377,"passed_time":4484.172676,"remaining_time":7378.718001},
{"learn":[118.1222346],"iteration":378,"passed_time":4497.435235,"remaining_time":7369.148499},
{"learn":[117.5420668],"iteration":379,"passed_time":4510.802258,"remaining_time":7359.729999},
{"learn":[115.7271161],"iteration":380,"passed_time":4523.318594,"remaining_time":7348.908687},
{"learn":[114.0375629],"iteration":381,"passed_time":4535.894607,"remaining_time":7338.175046},
{"learn":[113.6261279],"iteration":382,"passed_time":4547.416205,"remaining_time":7325.733156},
{"learn":[112.7925059],"iteration":383,"passed_time":4560.723594,"remaining_time":7316.160766},
{"learn":[111.3822288],"iteration":384,"passed_time":4573.275987,"remaining_time":7305.36294},
{"learn":[110.0587623],"iteration":385,"passed_time":4584.882963,"remaining_time":7293.052175},
{"learn":[110.0461385],"iteration":386,"passed_time":4584.919787,"remaining_time":7262.418163},
{"learn":[109.4638969],"iteration":387,"passed_time":4597.103312,"remaining_time":7251.101101},
{"learn":[108.8163019],"iteration":388,"passed_time":4609.834854,"remaining_time":7240.640349},
{"learn":[108.0279281],"iteration":389,"passed_time":4622.427172,"remaining_time":7229.950192},
{"learn":[106.6490613],"iteration":390,"passed_time":4635.096915,"remaining_time":7219.370898},
{"learn":[104.7973838],"iteration":391,"passed_time":4648.040612,"remaining_time":7209.205847},
{"learn":[103.8621639],"iteration":392,"passed_time":4660.242943,"remaining_time":7197.881594},
{"learn":[102.9864001],"iteration":393,"passed_time":4673.03663,"remaining_time":7187.46243},
{"learn":[102.3851195],"iteration":394,"passed_time":4685.406435,"remaining_time":7176.382008},
{"learn":[101.1526929],"iteration":395,"passed_time":4697.64073,"remaining_time":7165.088386},
{"learn":[100.7698657],"iteration":396,"passed_time":4710.056126,"remaining_time":7154.065098},
{"learn":[99.94534232],"iteration":397,"passed_time":4722.7448,"remaining_time":7143.448165},
{"learn":[98.74169321],"iteration":398,"passed_time":4735.637516,"remaining_time":7133.128188},
{"learn":[97.2516317],"iteration":399,"passed_time":4748.089509,"remaining_time":7122.134263},
{"learn":[96.60573771],"iteration":400,"passed_time":4761.001063,"remaining_time":7111.819542},
{"learn":[95.73160676],"iteration":401,"passed_time":4772.871612,"remaining_time":7099.943343},
{"learn":[94.70778795],"iteration":402,"passed_time":4786.117091,"remaining_time":7090.103978},
{"learn":[94.69880198],"iteration":403,"passed_time":4786.184154,"remaining_time":7060.806325},
{"learn":[94.01917469],"iteration":404,"passed_time":4798.472247,"remaining_time":7049.607375},
{"learn":[93.50711954],"iteration":405,"passed_time":4810.081144,"remaining_time":7037.409358},
{"learn":[92.70915365],"iteration":406,"passed_time":4822.022239,"remaining_time":7025.69825},
{"learn":[91.9672419],"iteration":407,"passed_time":4835.154804,"remaining_time":7015.714814},
{"learn":[90.72186768],"iteration":408,"passed_time":4848.106277,"remaining_time":7005.454302},
{"learn":[89.82638304],"iteration":409,"passed_time":4860.539628,"remaining_time":6994.435075},
{"learn":[88.42597471],"iteration":410,"passed_time":4871.845941,"remaining_time":6981.793819},
{"learn":[87.66544812],"iteration":411,"passed_time":4884.966932,"remaining_time":6971.748922},
{"learn":[86.73739522],"iteration":412,"passed_time":4897.407823,"remaining_time":6960.722499},
{"learn":[86.02425678],"iteration":413,"passed_time":4909.245221,"remaining_time":6948.835023},
{"learn":[84.98862989],"iteration":414,"passed_time":4921.838898,"remaining_time":6938.013869},
{"learn":[83.93492163],"iteration":415,"passed_time":4934.265869,"remaining_time":6926.950163},
{"learn":[83.21105687],"iteration":416,"passed_time":4947.148899,"remaining_time":6916.517526},
{"learn":[82.4948637],"iteration":417,"passed_time":4959.613864,"remaining_time":6905.491073},
{"learn":[82.01933788],"iteration":418,"passed_time":4972.144669,"remaining_time":6894.549052},
{"learn":[81.05808303],"iteration":419,"passed_time":4984.791022,"remaining_time":6883.759031},
{"learn":[80.59781237],"iteration":420,"passed_time":4997.481514,"remaining_time":6873.020895},
{"learn":[80.20293678],"iteration":421,"passed_time":5009.379763,"remaining_time":6861.188396},
{"learn":[79.07008898],"iteration":422,"passed_time":5021.959894,"remaining_time":6850.285719},
{"learn":[78.44590701],"iteration":423,"passed_time":5034.455346,"remaining_time":6839.260092},
{"learn":[77.72503882],"iteration":424,"passed_time":5047.191587,"remaining_time":6828.553323},
{"learn":[76.0211867],"iteration":425,"passed_time":5059.795202,"remaining_time":6817.658324},
{"learn":[75.5031256],"iteration":426,"passed_time":5073.191106,"remaining_time":6807.81851},
{"learn":[74.57554741],"iteration":427,"passed_time":5085.206274,"remaining_time":6796.116796},
{"learn":[74.22963533],"iteration":428,"passed_time":5097.662178,"remaining_time":6785.000241},
{"learn":[73.80382212],"iteration":429,"passed_time":5109.785424,"remaining_time":6773.436493},
{"learn":[72.62695322],"iteration":430,"passed_time":5123.085815,"remaining_time":6763.424197},
{"learn":[72.34406669],"iteration":431,"passed_time":5135.314556,"remaining_time":6751.987657},
{"learn":[71.98674865],"iteration":432,"passed_time":5147.25269,"remaining_time":6740.166918},
{"learn":[71.0334304],"iteration":433,"passed_time":5159.846786,"remaining_time":6729.201107},
{"learn":[70.04023572],"iteration":434,"passed_time":5172.062243,"remaining_time":6717.736017},
{"learn":[69.68830086],"iteration":435,"passed_time":5184.343191,"remaining_time":6706.352201},
{"learn":[68.91410327],"iteration":436,"passed_time":5196.286743,"remaining_time":6694.529603},
{"learn":[68.6821726],"iteration":437,"passed_time":5209.246534,"remaining_time":6684.010393},
{"learn":[67.76923848],"iteration":438,"passed_time":5221.304929,"remaining_time":6672.328167},
{"learn":[67.19085454],"iteration":439,"passed_time":5234.201283,"remaining_time":6661.710724},
{"learn":[66.81094818],"iteration":440,"passed_time":5247.038445,"remaining_time":6651.007916},
{"learn":[66.18486531],"iteration":441,"passed_time":5259.053459,"remaining_time":6639.257534},
{"learn":[65.2142976],"iteration":442,"passed_time":5271.734553,"remaining_time":6628.343445},
{"learn":[65.10667679],"iteration":443,"passed_time":5284.379754,"remaining_time":6617.376449},
{"learn":[64.17758223],"iteration":444,"passed_time":5296.671301,"remaining_time":6605.960836},
{"learn":[63.55784708],"iteration":445,"passed_time":5309.397401,"remaining_time":6595.081076},
{"learn":[63.15169367],"iteration":446,"passed_time":5322.725627,"remaining_time":6584.937968},
{"learn":[63.13453945],"iteration":447,"passed_time":5323.155605,"remaining_time":6558.888156},
{"learn":[62.87430352],"iteration":448,"passed_time":5335.493371,"remaining_time":6547.565362},
{"learn":[62.58018624],"iteration":449,"passed_time":5348.22074,"remaining_time":6536.714237},
{"learn":[62.3739172],"iteration":450,"passed_time":5361.085734,"remaining_time":6526.022323},
{"learn":[61.58068983],"iteration":451,"passed_time":5374.445487,"remaining_time":6515.920635},
{"learn":[60.77353241],"iteration":452,"passed_time":5387.263384,"remaining_time":6505.150268},
{"learn":[60.36165611],"iteration":453,"passed_time":5399.630982,"remaining_time":6493.829331},
{"learn":[60.25369829],"iteration":454,"passed_time":5404.328596,"remaining_time":6473.31667},
{"learn":[59.66137012],"iteration":455,"passed_time":5417.020044,"remaining_time":6462.409877},
{"learn":[58.65594118],"iteration":456,"passed_time":5428.952205,"remaining_time":6450.593101},
{"learn":[58.18354112],"iteration":457,"passed_time":5441.864505,"remaining_time":6439.935724},
{"learn":[57.4254932],"iteration":458,"passed_time":5454.273007,"remaining_time":6428.674721},
{"learn":[57.41636497],"iteration":459,"passed_time":5454.344156,"remaining_time":6402.925748},
{"learn":[57.21661535],"iteration":460,"passed_time":5466.752437,"remaining_time":6391.712719},
{"learn":[57.11161202],"iteration":461,"passed_time":5479.124898,"remaining_time":6380.452803},
{"learn":[57.10397008],"iteration":462,"passed_time":5479.223019,"remaining_time":6354.951968},
{"learn":[56.90326501],"iteration":463,"passed_time":5491.453798,"remaining_time":6343.575939},
{"learn":[56.63499545],"iteration":464,"passed_time":5503.827705,"remaining_time":6332.360908},
{"learn":[56.3258535],"iteration":465,"passed_time":5516.273882,"remaining_time":6321.223719},
{"learn":[55.84450478],"iteration":466,"passed_time":5528.781356,"remaining_time":6310.150884},
{"learn":[55.37873334],"iteration":467,"passed_time":5540.31111,"remaining_time":6297.960493},
{"learn":[55.3697469],"iteration":468,"passed_time":5540.889576,"remaining_time":6273.373913},
{"learn":[55.07870553],"iteration":469,"passed_time":5553.320166,"remaining_time":6262.254655},
{"learn":[54.40527421],"iteration":470,"passed_time":5566.721475,"remaining_time":6252.220085},
{"learn":[53.89248395],"iteration":471,"passed_time":5579.070706,"remaining_time":6240.994349},
{"learn":[53.35252792],"iteration":472,"passed_time":5591.766449,"remaining_time":6230.149934},
{"learn":[52.94136024],"iteration":473,"passed_time":5604.53131,"remaining_time":6219.374407},
{"learn":[52.87927216],"iteration":474,"passed_time":5616.984672,"remaining_time":6208.246217},
{"learn":[52.09258103],"iteration":475,"passed_time":5629.307671,"remaining_time":6196.968949},
{"learn":[51.29069328],"iteration":476,"passed_time":5641.938264,"remaining_time":6186.024553},
{"learn":[51.28103947],"iteration":477,"passed_time":5642.206616,"remaining_time":6161.572915},
{"learn":[50.74873696],"iteration":478,"passed_time":5654.594956,"remaining_time":6150.404952},
{"learn":[50.34095305],"iteration":479,"passed_time":5667.936309,"remaining_time":6140.264335},
{"learn":[49.86512093],"iteration":480,"passed_time":5681.23177,"remaining_time":6130.060891},
{"learn":[49.28517035],"iteration":481,"passed_time":5692.610971,"remaining_time":6117.785235},
{"learn":[48.99760047],"iteration":482,"passed_time":5704.986158,"remaining_time":6106.579387},
{"learn":[48.73262914],"iteration":483,"passed_time":5717.213494,"remaining_time":6095.21108},
{"learn":[48.23596978],"iteration":484,"passed_time":5729.806253,"remaining_time":6084.227258},
{"learn":[47.72686045],"iteration":485,"passed_time":5742.322845,"remaining_time":6073.15626},
{"learn":[47.13373362],"iteration":486,"passed_time":5754.444829,"remaining_time":6061.66365},
{"learn":[46.77013927],"iteration":487,"passed_time":5766.936045,"remaining_time":6050.555851},
{"learn":[46.38798639],"iteration":488,"passed_time":5779.909586,"remaining_time":6039.946418},
{"learn":[46.08675625],"iteration":489,"passed_time":5792.668927,"remaining_time":6029.104393},
{"learn":[45.8822118],"iteration":490,"passed_time":5805.482298,"remaining_time":6018.31057},
{"learn":[45.78059869],"iteration":491,"passed_time":5817.936527,"remaining_time":6007.137715},
{"learn":[45.25032269],"iteration":492,"passed_time":5830.486723,"remaining_time":5996.058354},
{"learn":[44.81052474],"iteration":493,"passed_time":5842.79335,"remaining_time":5984.723553},
{"learn":[44.58884524],"iteration":494,"passed_time":5855.676512,"remaining_time":5973.973008},
{"learn":[43.98062911],"iteration":495,"passed_time":5868.595233,"remaining_time":5963.249995},
{"learn":[43.51634884],"iteration":496,"passed_time":5881.385314,"remaining_time":5952.387954},
{"learn":[43.05243417],"iteration":497,"passed_time":5893.840599,"remaining_time":5941.180684},
{"learn":[42.46797216],"iteration":498,"passed_time":5906.32114,"remaining_time":5929.99377},
{"learn":[42.41419369],"iteration":499,"passed_time":5917.58784,"remaining_time":5917.58784},
{"learn":[42.07030617],"iteration":500,"passed_time":5929.597487,"remaining_time":5905.926439},
{"learn":[41.76895588],"iteration":501,"passed_time":5941.241838,"remaining_time":5893.901265},
{"learn":[41.31910754],"iteration":502,"passed_time":5953.730444,"remaining_time":5882.711791},
{"learn":[41.04396338],"iteration":503,"passed_time":5966.302969,"remaining_time":5871.599748},
{"learn":[40.63152385],"iteration":504,"passed_time":5979.032523,"remaining_time":5860.635839},
{"learn":[40.18745427],"iteration":505,"passed_time":5991.316307,"remaining_time":5849.229754},
{"learn":[39.71341611],"iteration":506,"passed_time":6003.692586,"remaining_time":5837.910148},
{"learn":[39.45729677],"iteration":507,"passed_time":6015.784026,"remaining_time":5826.310513},
{"learn":[39.26507927],"iteration":508,"passed_time":6028.46238,"remaining_time":5815.275105},
{"learn":[38.60071546],"iteration":509,"passed_time":6040.28403,"remaining_time":5803.410147},
{"learn":[38.29463702],"iteration":510,"passed_time":6053.1133,"remaining_time":5792.509596},
{"learn":[37.88736938],"iteration":511,"passed_time":6065.695402,"remaining_time":5781.36593},
{"learn":[37.42119141],"iteration":512,"passed_time":6078.69199,"remaining_time":5770.610135},
{"learn":[37.04647758],"iteration":513,"passed_time":6090.920762,"remaining_time":5759.119631},
{"learn":[37.03886028],"iteration":514,"passed_time":6091.122297,"remaining_time":5736.299639},
{"learn":[36.77889311],"iteration":515,"passed_time":6103.205487,"remaining_time":5724.712123},
{"learn":[36.45330463],"iteration":516,"passed_time":6115.691832,"remaining_time":5713.499333},
{"learn":[35.91739746],"iteration":517,"passed_time":6128.142274,"remaining_time":5702.248216},
{"learn":[35.91149221],"iteration":518,"passed_time":6129.613845,"remaining_time":5680.817455},
{"learn":[35.65463028],"iteration":519,"passed_time":6142.469553,"remaining_time":5669.971895},
{"learn":[35.54136201],"iteration":520,"passed_time":6154.946447,"remaining_time":5658.770342},
{"learn":[35.19766815],"iteration":521,"passed_time":6167.458961,"remaining_time":5647.59652},
{"learn":[35.06049619],"iteration":522,"passed_time":6179.596488,"remaining_time":5636.075573},
{"learn":[35.05395033],"iteration":523,"passed_time":6179.918307,"remaining_time":5613.81892},
{"learn":[35.01812892],"iteration":524,"passed_time":6191.973098,"remaining_time":5602.261374},
{"learn":[34.57824598],"iteration":525,"passed_time":6204.704185,"remaining_time":5591.311376},
{"learn":[34.01169444],"iteration":526,"passed_time":6217.522874,"remaining_time":5580.433244},
{"learn":[33.81784158],"iteration":527,"passed_time":6230.434029,"remaining_time":5569.63042},
{"learn":[33.40749379],"iteration":528,"passed_time":6243.652875,"remaining_time":5559.09358},
{"learn":[33.04343114],"iteration":529,"passed_time":6256.419676,"remaining_time":5548.14575},
{"learn":[33.04033689],"iteration":530,"passed_time":6256.436984,"remaining_time":5525.930218},
{"learn":[32.53420853],"iteration":531,"passed_time":6268.998159,"remaining_time":5514.832967},
{"learn":[32.32611426],"iteration":532,"passed_time":6281.510329,"remaining_time":5503.687287},
{"learn":[32.11878194],"iteration":533,"passed_time":6293.502647,"remaining_time":5492.082834},
{"learn":[32.11462694],"iteration":534,"passed_time":6293.572563,"remaining_time":5470.114471},
{"learn":[32.11102816],"iteration":535,"passed_time":6293.883639,"remaining_time":5448.436583},
{"learn":[31.69720222],"iteration":536,"passed_time":6306.079112,"remaining_time":5437.08497},
{"learn":[31.39725465],"iteration":537,"passed_time":6318.541581,"remaining_time":5425.959499},
{"learn":[31.27389024],"iteration":538,"passed_time":6331.070299,"remaining_time":5414.885729},
{"learn":[30.80460565],"iteration":539,"passed_time":6344.444689,"remaining_time":5404.526957},
{"learn":[30.72133247],"iteration":540,"passed_time":6357.718383,"remaining_time":5394.071604},
{"learn":[30.46208778],"iteration":541,"passed_time":6370.344588,"remaining_time":5383.058711},
{"learn":[30.35632557],"iteration":542,"passed_time":6382.698519,"remaining_time":5371.810724},
{"learn":[30.20164359],"iteration":543,"passed_time":6394.952394,"remaining_time":5360.474801},
{"learn":[30.19975951],"iteration":544,"passed_time":6394.962659,"remaining_time":5338.91378},
{"learn":[30.00244943],"iteration":545,"passed_time":6407.004191,"remaining_time":5327.435719},
{"learn":[29.77259243],"iteration":546,"passed_time":6419.823395,"remaining_time":5316.599631},
{"learn":[29.56851892],"iteration":547,"passed_time":6432.04108,"remaining_time":5305.260161},
{"learn":[29.42843574],"iteration":548,"passed_time":6444.518576,"remaining_time":5294.130925},
{"learn":[29.35312763],"iteration":549,"passed_time":6457.292503,"remaining_time":5283.23932},
{"learn":[29.30438666],"iteration":550,"passed_time":6469.858055,"remaining_time":5272.171083},
{"learn":[29.11966569],"iteration":551,"passed_time":6482.19299,"remaining_time":5260.910253},
{"learn":[28.74999888],"iteration":552,"passed_time":6494.603312,"remaining_time":5249.706475},
{"learn":[28.39579908],"iteration":553,"passed_time":6507.530577,"remaining_time":5238.914507},
{"learn":[27.97285915],"iteration":554,"passed_time":6519.877398,"remaining_time":5227.649445},
{"learn":[27.66126162],"iteration":555,"passed_time":6531.46177,"remaining_time":5215.771629},
{"learn":[27.55650719],"iteration":556,"passed_time":6544.256629,"remaining_time":5204.857606},
{"learn":[27.45668727],"iteration":557,"passed_time":6556.813266,"remaining_time":5193.748142},
{"learn":[27.11347406],"iteration":558,"passed_time":6567.963565,"remaining_time":5181.524029},
{"learn":[26.85018108],"iteration":559,"passed_time":6580.479277,"remaining_time":5170.376575},
{"learn":[26.71154969],"iteration":560,"passed_time":6593.779497,"remaining_time":5159.838145},
{"learn":[26.58169091],"iteration":561,"passed_time":6606.530309,"remaining_time":5148.8617},
{"learn":[26.39261647],"iteration":562,"passed_time":6619.442003,"remaining_time":5138.003828},
{"learn":[26.15871836],"iteration":563,"passed_time":6631.198744,"remaining_time":5126.245838},
{"learn":[25.95010128],"iteration":564,"passed_time":6643.728667,"remaining_time":5115.083133},
{"learn":[25.77883295],"iteration":565,"passed_time":6656.55567,"remaining_time":5104.143394},
{"learn":[25.39185529],"iteration":566,"passed_time":6669.795248,"remaining_time":5093.512068},
{"learn":[25.26309145],"iteration":567,"passed_time":6682.4212,"remaining_time":5082.404857},
{"learn":[25.02401676],"iteration":568,"passed_time":6694.886457,"remaining_time":5071.170585},
{"learn":[24.8910747],"iteration":569,"passed_time":6707.046997,"remaining_time":5059.70212},
{"learn":[24.58438959],"iteration":570,"passed_time":6719.317836,"remaining_time":5048.314101},
{"learn":[24.42894036],"iteration":571,"passed_time":6732.36431,"remaining_time":5037.503365},
{"learn":[24.34241596],"iteration":572,"passed_time":6744.303955,"remaining_time":5025.860015},
{"learn":[24.15229319],"iteration":573,"passed_time":6756.670937,"remaining_time":5014.532786},
{"learn":[23.92673357],"iteration":574,"passed_time":6768.897124,"remaining_time":5003.097874},
{"learn":[23.72719262],"iteration":575,"passed_time":6782.048058,"remaining_time":4992.340932},
{"learn":[23.65402741],"iteration":576,"passed_time":6794.700562,"remaining_time":4981.210291},
{"learn":[23.61265067],"iteration":577,"passed_time":6806.975017,"remaining_time":4969.798369},
{"learn":[23.50909042],"iteration":578,"passed_time":6819.985203,"remaining_time":4958.918429},
{"learn":[23.37281772],"iteration":579,"passed_time":6832.505099,"remaining_time":4947.676106},
{"learn":[23.32527349],"iteration":580,"passed_time":6844.944779,"remaining_time":4936.371536},
{"learn":[23.17648549],"iteration":581,"passed_time":6857.744984,"remaining_time":4925.321999},
{"learn":[23.03593297],"iteration":582,"passed_time":6870.197927,"remaining_time":4914.018071},
{"learn":[22.82034492],"iteration":583,"passed_time":6882.687015,"remaining_time":4902.735956},
{"learn":[22.66656239],"iteration":584,"passed_time":6895.228618,"remaining_time":4891.486968},
{"learn":[22.28523223],"iteration":585,"passed_time":6908.155697,"remaining_time":4880.505902},
{"learn":[22.00444627],"iteration":586,"passed_time":6920.796155,"remaining_time":4869.316545},
{"learn":[21.86195252],"iteration":587,"passed_time":6933.211973,"remaining_time":4857.964852},
{"learn":[21.8558499],"iteration":588,"passed_time":6945.18417,"remaining_time":4846.299989},
{"learn":[21.73960539],"iteration":589,"passed_time":6957.44471,"remaining_time":4834.834459},
{"learn":[21.45049125],"iteration":590,"passed_time":6969.714471,"remaining_time":4823.37262},
{"learn":[21.11067027],"iteration":591,"passed_time":6982.374154,"remaining_time":4812.176782},
{"learn":[20.83705038],"iteration":592,"passed_time":6994.862496,"remaining_time":4800.858408},
{"learn":[20.62350564],"iteration":593,"passed_time":7007.761433,"remaining_time":4789.816737},
{"learn":[20.37557771],"iteration":594,"passed_time":7019.948167,"remaining_time":4778.284047},
{"learn":[20.21779446],"iteration":595,"passed_time":7032.14747,"remaining_time":4766.757681},
{"learn":[20.11841427],"iteration":596,"passed_time":7044.431454,"remaining_time":4755.286224},
{"learn":[20.02364333],"iteration":597,"passed_time":7057.178092,"remaining_time":4744.123065},
{"learn":[19.92562655],"iteration":598,"passed_time":7069.783783,"remaining_time":4732.860262},
{"learn":[19.83707407],"iteration":599,"passed_time":7082.569601,"remaining_time":4721.713067},
{"learn":[19.62248378],"iteration":600,"passed_time":7095.210923,"remaining_time":4710.46449},
{"learn":[19.53804474],"iteration":601,"passed_time":7107.796804,"remaining_time":4699.174631},
{"learn":[19.49218427],"iteration":602,"passed_time":7120.499168,"remaining_time":4687.957164},
{"learn":[19.22735745],"iteration":603,"passed_time":7133.161263,"remaining_time":4676.708378},
{"learn":[19.01916851],"iteration":604,"passed_time":7146.396305,"remaining_time":4665.828992},
{"learn":[18.78711622],"iteration":605,"passed_time":7158.686093,"remaining_time":4654.327262},
{"learn":[18.61367641],"iteration":606,"passed_time":7171.382306,"remaining_time":4643.086073},
{"learn":[18.38315401],"iteration":607,"passed_time":7184.16039,"remaining_time":4631.892883},
{"learn":[18.23070101],"iteration":608,"passed_time":7196.538415,"remaining_time":4620.437636},
{"learn":[18.03625335],"iteration":609,"passed_time":7209.197831,"remaining_time":4609.159269},
{"learn":[17.9151828],"iteration":610,"passed_time":7221.685296,"remaining_time":4597.766907},
{"learn":[17.80387737],"iteration":611,"passed_time":7235.075488,"remaining_time":4586.943284},
{"learn":[17.71003945],"iteration":612,"passed_time":7247.483209,"remaining_time":4575.491031},
{"learn":[17.49377278],"iteration":613,"passed_time":7259.707352,"remaining_time":4563.920257},
{"learn":[17.35867747],"iteration":614,"passed_time":7271.912633,"remaining_time":4552.335551},
{"learn":[17.30538528],"iteration":615,"passed_time":7284.045492,"remaining_time":4540.703683},
{"learn":[17.24696447],"iteration":616,"passed_time":7296.957421,"remaining_time":4529.553796},
{"learn":[17.2147303],"iteration":617,"passed_time":7309.706201,"remaining_time":4518.297361},
{"learn":[17.00363914],"iteration":618,"passed_time":7322.250562,"remaining_time":4506.910281},
{"learn":[16.77608781],"iteration":619,"passed_time":7335.067094,"remaining_time":4495.686283},
{"learn":[16.55430567],"iteration":620,"passed_time":7348.154188,"remaining_time":4484.622282},
{"learn":[16.45801969],"iteration":621,"passed_time":7360.102132,"remaining_time":4472.859495},
{"learn":[16.29548574],"iteration":622,"passed_time":7372.728053,"remaining_time":4461.506382},
{"learn":[16.05809724],"iteration":623,"passed_time":7386.04836,"remaining_time":4450.567601},
{"learn":[16.02250315],"iteration":624,"passed_time":7398.527196,"remaining_time":4439.116317},
{"learn":[15.92945295],"iteration":625,"passed_time":7411.071607,"remaining_time":4427.700928},
{"learn":[15.85977664],"iteration":626,"passed_time":7424.230558,"remaining_time":4416.647525},
{"learn":[15.70596706],"iteration":627,"passed_time":7437.02522,"remaining_time":4405.371627},
{"learn":[15.54870063],"iteration":628,"passed_time":7450.455701,"remaining_time":4394.465922},
{"learn":[15.35877679],"iteration":629,"passed_time":7462.969836,"remaining_time":4383.014031},
{"learn":[15.34725926],"iteration":630,"passed_time":7468.889421,"remaining_time":4367.702372},
{"learn":[15.21500245],"iteration":631,"passed_time":7482.050231,"remaining_time":4356.636843},
{"learn":[15.02402099],"iteration":632,"passed_time":7493.59132,"remaining_time":4344.625616},
{"learn":[14.88237509],"iteration":633,"passed_time":7506.62536,"remaining_time":4333.477731},
{"learn":[14.67797572],"iteration":634,"passed_time":7519.088731,"remaining_time":4321.995885},
{"learn":[14.56173939],"iteration":635,"passed_time":7531.451446,"remaining_time":4310.453344},
{"learn":[14.45337811],"iteration":636,"passed_time":7543.820295,"remaining_time":4298.911722},
{"learn":[14.4190266],"iteration":637,"passed_time":7556.129298,"remaining_time":4287.333551},
{"learn":[14.17795505],"iteration":638,"passed_time":7568.887811,"remaining_time":4276.007042},
{"learn":[14.08281767],"iteration":639,"passed_time":7581.151007,"remaining_time":4264.397442},
{"learn":[13.93416882],"iteration":640,"passed_time":7593.985059,"remaining_time":4253.105517},
{"learn":[13.79761199],"iteration":641,"passed_time":7605.49012,"remaining_time":4241.067699},
{"learn":[13.65667505],"iteration":642,"passed_time":7618.703395,"remaining_time":4229.979957},
{"learn":[13.50845502],"iteration":643,"passed_time":7631.547598,"remaining_time":4218.681592},
{"learn":[13.40526298],"iteration":644,"passed_time":7643.797793,"remaining_time":4207.051499},
{"learn":[13.3032582],"iteration":645,"passed_time":7655.920045,"remaining_time":4195.349374},
{"learn":[13.13115811],"iteration":646,"passed_time":7667.741128,"remaining_time":4183.481636},
{"learn":[13.09881943],"iteration":647,"passed_time":7679.717872,"remaining_time":4171.698597},
{"learn":[13.02283432],"iteration":648,"passed_time":7692.311541,"remaining_time":4160.248615},
{"learn":[12.88999326],"iteration":649,"passed_time":7705.083448,"remaining_time":4148.891087},
{"learn":[12.79379466],"iteration":650,"passed_time":7717.699544,"remaining_time":4137.445685},
{"learn":[12.65629053],"iteration":651,"passed_time":7729.638166,"remaining_time":4125.635095},
{"learn":[12.51219781],"iteration":652,"passed_time":7742.33596,"remaining_time":4114.227532},
{"learn":[12.38754587],"iteration":653,"passed_time":7754.91961,"remaining_time":4102.755635},
{"learn":[12.31163977],"iteration":654,"passed_time":7767.392596,"remaining_time":4091.222054},
{"learn":[12.18683389],"iteration":655,"passed_time":7779.821027,"remaining_time":4079.662246},
{"learn":[12.09436228],"iteration":656,"passed_time":7792.537772,"remaining_time":4068.250313},
{"learn":[12.00631193],"iteration":657,"passed_time":7804.648127,"remaining_time":4056.519239},
{"learn":[11.91426782],"iteration":658,"passed_time":7817.967686,"remaining_time":4045.412718},
{"learn":[11.83267091],"iteration":659,"passed_time":7829.825642,"remaining_time":4033.546543},
{"learn":[11.76955038],"iteration":660,"passed_time":7842.468336,"remaining_time":4022.082853},
{"learn":[11.70571194],"iteration":661,"passed_time":7854.827042,"remaining_time":4010.470605},
{"learn":[11.70292446],"iteration":662,"passed_time":7855.691582,"remaining_time":3993.01367},
{"learn":[11.68650667],"iteration":663,"passed_time":7859.273252,"remaining_time":3976.981646},
{"learn":[11.53660677],"iteration":664,"passed_time":7871.895925,"remaining_time":3965.541556},
{"learn":[11.43422752],"iteration":665,"passed_time":7884.13725,"remaining_time":3953.906669},
{"learn":[11.36283833],"iteration":666,"passed_time":7897.161034,"remaining_time":3942.660606},
{"learn":[11.32567509],"iteration":667,"passed_time":7910.257285,"remaining_time":3931.445237},
{"learn":[11.18216436],"iteration":668,"passed_time":7923.085422,"remaining_time":3920.091591},
{"learn":[11.134184],"iteration":669,"passed_time":7936.756194,"remaining_time":3909.148573},
{"learn":[11.05017345],"iteration":670,"passed_time":7949.353977,"remaining_time":3897.671324},
{"learn":[10.94415351],"iteration":671,"passed_time":7961.894812,"remaining_time":3886.162944},
{"learn":[10.82820782],"iteration":672,"passed_time":7974.13463,"remaining_time":3874.505236},
{"learn":[10.73374621],"iteration":673,"passed_time":7987.154046,"remaining_time":3863.222877},
{"learn":[10.67995573],"iteration":674,"passed_time":7999.879729,"remaining_time":3851.793944},
{"learn":[10.55279998],"iteration":675,"passed_time":8012.292127,"remaining_time":3840.211019},
{"learn":[10.44694489],"iteration":676,"passed_time":8025.362464,"remaining_time":3828.939551},
{"learn":[10.38725386],"iteration":677,"passed_time":8038.298968,"remaining_time":3817.599215},
{"learn":[10.30248458],"iteration":678,"passed_time":8050.796748,"remaining_time":3806.046769},
{"learn":[10.26028386],"iteration":679,"passed_time":8063.526693,"remaining_time":3794.600797},
{"learn":[10.22747588],"iteration":680,"passed_time":8074.891143,"remaining_time":3782.511416},
{"learn":[10.04291782],"iteration":681,"passed_time":8084.888871,"remaining_time":3769.786893},
{"learn":[9.974216664],"iteration":682,"passed_time":8093.988614,"remaining_time":3756.653573},
{"learn":[9.839859582],"iteration":683,"passed_time":8103.4998,"remaining_time":3743.72213},
{"learn":[9.779176524],"iteration":684,"passed_time":8112.365854,"remaining_time":3730.504006},
{"learn":[9.733639942],"iteration":685,"passed_time":8121.470222,"remaining_time":3717.407653},
{"learn":[9.675799844],"iteration":686,"passed_time":8130.746168,"remaining_time":3704.401093},
{"learn":[9.54995221],"iteration":687,"passed_time":8139.822994,"remaining_time":3691.315079},
{"learn":[9.439138541],"iteration":688,"passed_time":8148.806905,"remaining_time":3678.198762},
{"learn":[9.347101319],"iteration":689,"passed_time":8157.687098,"remaining_time":3665.047827},
{"learn":[9.256616582],"iteration":690,"passed_time":8167.073369,"remaining_time":3652.135559},
{"learn":[9.135892733],"iteration":691,"passed_time":8176.481625,"remaining_time":3639.243267},
{"learn":[9.067346092],"iteration":692,"passed_time":8185.303925,"remaining_time":3626.10145},
{"learn":[9.004759615],"iteration":693,"passed_time":8193.240586,"remaining_time":3612.581584},
{"learn":[8.981151012],"iteration":694,"passed_time":8201.61023,"remaining_time":3599.267799},
{"learn":[8.875978273],"iteration":695,"passed_time":8209.908296,"remaining_time":3585.936957},
{"learn":[8.801105914],"iteration":696,"passed_time":8218.160469,"remaining_time":3572.600606},
{"learn":[8.719751349],"iteration":697,"passed_time":8226.621101,"remaining_time":3559.369015},
{"learn":[8.596051499],"iteration":698,"passed_time":8234.886724,"remaining_time":3546.067101},
{"learn":[8.539951901],"iteration":699,"passed_time":8242.418537,"remaining_time":3532.465087},
{"learn":[8.520738084],"iteration":700,"passed_time":8250.464854,"remaining_time":3519.099845},
{"learn":[8.474329414],"iteration":701,"passed_time":8258.884367,"remaining_time":3505.908178},
{"learn":[8.42554007],"iteration":702,"passed_time":8267.505678,"remaining_time":3492.815343},
{"learn":[8.401904628],"iteration":703,"passed_time":8275.946632,"remaining_time":3479.659379},
{"learn":[8.294236451],"iteration":704,"passed_time":8283.96396,"remaining_time":3466.339529},
{"learn":[8.202706814],"iteration":705,"passed_time":8292.468533,"remaining_time":3453.237604},
{"learn":[8.12427374],"iteration":706,"passed_time":8300.803677,"remaining_time":3440.078469},
{"learn":[8.074587793],"iteration":707,"passed_time":8309.251138,"remaining_time":3426.979283},
{"learn":[8.009163772],"iteration":708,"passed_time":8317.400608,"remaining_time":3413.770912},
{"learn":[7.965785662],"iteration":709,"passed_time":8325.871545,"remaining_time":3400.708096},
{"learn":[7.90576076],"iteration":710,"passed_time":8334.370814,"remaining_time":3387.669712},
{"learn":[7.826360203],"iteration":711,"passed_time":8342.218133,"remaining_time":3374.380368},
{"learn":[7.81628171],"iteration":712,"passed_time":8349.745527,"remaining_time":3360.977512},
{"learn":[7.72793307],"iteration":713,"passed_time":8354.686738,"remaining_time":3346.555192},
{"learn":[7.657772202],"iteration":714,"passed_time":8359.579805,"remaining_time":3332.140202},
{"learn":[7.562430918],"iteration":715,"passed_time":8364.058001,"remaining_time":3317.587252},
{"learn":[7.561749578],"iteration":716,"passed_time":8364.125948,"remaining_time":3301.321678},
{"learn":[7.521753045],"iteration":717,"passed_time":8368.466402,"remaining_time":3286.779283},
{"learn":[7.473217188],"iteration":718,"passed_time":8372.979741,"remaining_time":3272.332833},
{"learn":[7.384504272],"iteration":719,"passed_time":8377.604906,"remaining_time":3257.957463},
{"learn":[7.327298251],"iteration":720,"passed_time":8382.179116,"remaining_time":3243.589422},
{"learn":[7.302490731],"iteration":721,"passed_time":8386.605818,"remaining_time":3229.191714},
{"learn":[7.228881375],"iteration":722,"passed_time":8390.906475,"remaining_time":3214.773297},
{"learn":[7.105207342],"iteration":723,"passed_time":8395.397491,"remaining_time":3200.455397},
{"learn":[7.062824193],"iteration":724,"passed_time":8400.472439,"remaining_time":3186.386098},
{"learn":[6.98680284],"iteration":725,"passed_time":8405.479245,"remaining_time":3172.315858},
{"learn":[6.943634204],"iteration":726,"passed_time":8409.902048,"remaining_time":3158.051251},
{"learn":[6.931786091],"iteration":727,"passed_time":8413.950444,"remaining_time":3143.673792},
{"learn":[6.883363998],"iteration":728,"passed_time":8418.030053,"remaining_time":3129.336275},
{"learn":[6.826711867],"iteration":729,"passed_time":8422.312526,"remaining_time":3115.101893},
{"learn":[6.807933622],"iteration":730,"passed_time":8426.413186,"remaining_time":3100.827835},
{"learn":[6.727346539],"iteration":731,"passed_time":8430.461128,"remaining_time":3086.562271},
{"learn":[6.654064767],"iteration":732,"passed_time":8434.623753,"remaining_time":3072.36636},
{"learn":[6.627496434],"iteration":733,"passed_time":8438.625984,"remaining_time":3058.139662},
{"learn":[6.525534846],"iteration":734,"passed_time":8442.962693,"remaining_time":3044.061379},
{"learn":[6.451162956],"iteration":735,"passed_time":8447.116489,"remaining_time":3029.943958},
{"learn":[6.354174488],"iteration":736,"passed_time":8451.217335,"remaining_time":3015.83468},
{"learn":[6.325064403],"iteration":737,"passed_time":8455.484812,"remaining_time":3001.811681},
{"learn":[6.289728184],"iteration":738,"passed_time":8459.569784,"remaining_time":2987.750627},
{"learn":[6.253447299],"iteration":739,"passed_time":8463.604401,"remaining_time":2973.698844},
{"learn":[6.193966851],"iteration":740,"passed_time":8467.878961,"remaining_time":2959.757963},
{"learn":[6.124364674],"iteration":741,"passed_time":8472.106983,"remaining_time":2945.826956},
{"learn":[6.018959461],"iteration":742,"passed_time":8476.117718,"remaining_time":2931.846909},
{"learn":[5.980192136],"iteration":743,"passed_time":8480.232422,"remaining_time":2917.929436},
{"learn":[5.978255958],"iteration":744,"passed_time":8481.148214,"remaining_time":2902.943348},
{"learn":[5.925648315],"iteration":745,"passed_time":8485.456567,"remaining_time":2889.150091},
{"learn":[5.856148489],"iteration":746,"passed_time":8489.548598,"remaining_time":2875.308963},
{"learn":[5.795641439],"iteration":747,"passed_time":8493.644829,"remaining_time":2861.495317},
{"learn":[5.733488361],"iteration":748,"passed_time":8497.800147,"remaining_time":2847.727419},
{"learn":[5.679234466],"iteration":749,"passed_time":8501.812515,"remaining_time":2833.937505},
{"learn":[5.662429506],"iteration":750,"passed_time":8505.954213,"remaining_time":2820.21651},
{"learn":[5.602920499],"iteration":751,"passed_time":8510.101116,"remaining_time":2806.522708},
{"learn":[5.511196324],"iteration":752,"passed_time":8514.241002,"remaining_time":2792.851962},
{"learn":[5.502271017],"iteration":753,"passed_time":8518.324576,"remaining_time":2779.188124},
{"learn":[5.468857354],"iteration":754,"passed_time":8522.446238,"remaining_time":2765.562024},
{"learn":[5.465652142],"iteration":755,"passed_time":8526.565465,"remaining_time":2751.960283},
{"learn":[5.449265087],"iteration":756,"passed_time":8530.739233,"remaining_time":2738.401101},
{"learn":[5.388430826],"iteration":757,"passed_time":8534.906013,"remaining_time":2724.864453},
{"learn":[5.310573394],"iteration":758,"passed_time":8539.019044,"remaining_time":2711.335428},
{"learn":[5.26639838],"iteration":759,"passed_time":8543.097472,"remaining_time":2697.820254},
{"learn":[5.215036463],"iteration":760,"passed_time":8547.207958,"remaining_time":2684.33995},
{"learn":[5.145781405],"iteration":761,"passed_time":8551.246533,"remaining_time":2670.861778},
{"learn":[5.120993687],"iteration":762,"passed_time":8555.387329,"remaining_time":2657.440101},
{"learn":[5.072839462],"iteration":763,"passed_time":8559.649303,"remaining_time":2644.080151},
{"learn":[5.04705035],"iteration":764,"passed_time":8563.831286,"remaining_time":2630.719415},
{"learn":[5.011175434],"iteration":765,"passed_time":8567.953428,"remaining_time":2617.364363},
{"learn":[4.951944349],"iteration":766,"passed_time":8572.070617,"remaining_time":2604.031882},
{"learn":[4.927403332],"iteration":767,"passed_time":8576.344249,"remaining_time":2590.770659},
{"learn":[4.901017256],"iteration":768,"passed_time":8580.520456,"remaining_time":2577.503544},
{"learn":[4.850988992],"iteration":769,"passed_time":8584.596447,"remaining_time":2564.230108},
{"learn":[4.811436661],"iteration":770,"passed_time":8588.690252,"remaining_time":2550.985821},
{"learn":[4.775043312],"iteration":771,"passed_time":8592.804434,"remaining_time":2537.771258},
{"learn":[4.720354256],"iteration":772,"passed_time":8597.048387,"remaining_time":2524.618349},
{"learn":[4.697014185],"iteration":773,"passed_time":8601.089598,"remaining_time":2511.429263},
{"learn":[4.656266587],"iteration":774,"passed_time":8605.140729,"remaining_time":2498.266663},
{"learn":[4.59299039],"iteration":775,"passed_time":8609.158914,"remaining_time":2485.118037},
{"learn":[4.549487076],"iteration":776,"passed_time":8613.255714,"remaining_time":2472.015475},
{"learn":[4.498826739],"iteration":777,"passed_time":8617.459137,"remaining_time":2458.966489},
{"learn":[4.434951895],"iteration":778,"passed_time":8621.630224,"remaining_time":2445.931039},
{"learn":[4.422136881],"iteration":779,"passed_time":8625.836785,"remaining_time":2432.928324},
{"learn":[4.387100103],"iteration":780,"passed_time":8629.966194,"remaining_time":2419.9265},
{"learn":[4.367280223],"iteration":781,"passed_time":8634.119594,"remaining_time":2406.954056},
{"learn":[4.345915544],"iteration":782,"passed_time":8638.362927,"remaining_time":2394.029061},
{"learn":[4.329123452],"iteration":783,"passed_time":8642.373452,"remaining_time":2381.062073},
{"learn":[4.287454462],"iteration":784,"passed_time":8646.508705,"remaining_time":2368.152066},
{"learn":[4.280593423],"iteration":785,"passed_time":8650.575036,"remaining_time":2355.245621},
{"learn":[4.22342216],"iteration":786,"passed_time":8654.764292,"remaining_time":2342.39491},
{"learn":[4.198541711],"iteration":787,"passed_time":8658.913463,"remaining_time":2329.555399},
{"learn":[4.149340864],"iteration":788,"passed_time":8663.120971,"remaining_time":2316.753517},
{"learn":[4.138507416],"iteration":789,"passed_time":8667.332657,"remaining_time":2303.974504},
{"learn":[4.106478749],"iteration":790,"passed_time":8671.525689,"remaining_time":2291.212224},
{"learn":[4.071043646],"iteration":791,"passed_time":8675.693095,"remaining_time":2278.464853},
{"learn":[4.020147801],"iteration":792,"passed_time":8679.787678,"remaining_time":2265.720113},
{"learn":[3.977570037],"iteration":793,"passed_time":8683.958569,"remaining_time":2253.016959},
{"learn":[3.945682414],"iteration":794,"passed_time":8688.051482,"remaining_time":2240.315162},
{"learn":[3.916724698],"iteration":795,"passed_time":8692.188848,"remaining_time":2227.646388},
{"learn":[3.901322115],"iteration":796,"passed_time":8696.261663,"remaining_time":2214.982582},
{"learn":[3.867351889],"iteration":797,"passed_time":8700.528951,"remaining_time":2202.389534},
{"learn":[3.867142758],"iteration":798,"passed_time":8700.54745,"remaining_time":2188.748483},
{"learn":[3.843539787],"iteration":799,"passed_time":8704.749466,"remaining_time":2176.187367},
{"learn":[3.823891467],"iteration":800,"passed_time":8708.96896,"remaining_time":2163.651465},
{"learn":[3.79286287],"iteration":801,"passed_time":8713.162359,"remaining_time":2151.129859},
{"learn":[3.75060802],"iteration":802,"passed_time":8717.255037,"remaining_time":2138.604287},
{"learn":[3.719788561],"iteration":803,"passed_time":8721.268517,"remaining_time":2126.080385},
{"learn":[3.679877785],"iteration":804,"passed_time":8725.466277,"remaining_time":2113.622266},
{"learn":[3.658574597],"iteration":805,"passed_time":8729.563012,"remaining_time":2101.160328},
{"learn":[3.623515267],"iteration":806,"passed_time":8733.600964,"remaining_time":2088.705063},
{"learn":[3.599437585],"iteration":807,"passed_time":8737.781492,"remaining_time":2076.304513},
{"learn":[3.577081249],"iteration":808,"passed_time":8741.839546,"remaining_time":2063.895369},
{"learn":[3.550108758],"iteration":809,"passed_time":8746.084017,"remaining_time":2051.550572},
{"learn":[3.538672318],"iteration":810,"passed_time":8750.318728,"remaining_time":2039.223477},
{"learn":[3.526692613],"iteration":811,"passed_time":8754.610892,"remaining_time":2026.929615},
{"learn":[3.519879587],"iteration":812,"passed_time":8754.686964,"remaining_time":2013.685685},
{"learn":[3.500390361],"iteration":813,"passed_time":8759.003056,"remaining_time":2001.442959},
{"learn":[3.468068267],"iteration":814,"passed_time":8763.188833,"remaining_time":1989.190103},
{"learn":[3.453440135],"iteration":815,"passed_time":8767.211958,"remaining_time":1976.920344},
{"learn":[3.431048747],"iteration":816,"passed_time":8771.28699,"remaining_time":1964.682398},
{"learn":[3.377294232],"iteration":817,"passed_time":8775.5225,"remaining_time":1952.500116},
{"learn":[3.352676516],"iteration":818,"passed_time":8779.637291,"remaining_time":1940.310561},
{"learn":[3.322877311],"iteration":819,"passed_time":8783.738222,"remaining_time":1928.137658},
{"learn":[3.312498535],"iteration":820,"passed_time":8787.928198,"remaining_time":1916.003834},
{"learn":[3.28602587],"iteration":821,"passed_time":8792.11595,"remaining_time":1903.888855},
{"learn":[3.268613441],"iteration":822,"passed_time":8796.249353,"remaining_time":1891.781453},
{"learn":[3.221432808],"iteration":823,"passed_time":8800.48905,"remaining_time":1879.716108},
{"learn":[3.195810976],"iteration":824,"passed_time":8804.5186,"remaining_time":1867.625158},
{"learn":[3.158338471],"iteration":825,"passed_time":8808.770259,"remaining_time":1855.600515},
{"learn":[3.122325308],"iteration":826,"passed_time":8813.014285,"remaining_time":1843.593073},
{"learn":[3.070215204],"iteration":827,"passed_time":8817.147011,"remaining_time":1831.581263},
{"learn":[3.02685713],"iteration":828,"passed_time":8821.19357,"remaining_time":1819.570688},
{"learn":[3.010556847],"iteration":829,"passed_time":8825.330495,"remaining_time":1807.597812},
{"learn":[2.990229756],"iteration":830,"passed_time":8829.619742,"remaining_time":1795.674773},
{"learn":[2.974303836],"iteration":831,"passed_time":8833.756522,"remaining_time":1783.739298},
{"learn":[2.953135642],"iteration":832,"passed_time":8837.872285,"remaining_time":1771.818333},
{"learn":[2.917802828],"iteration":833,"passed_time":8842.135813,"remaining_time":1759.945497},
{"learn":[2.908469159],"iteration":834,"passed_time":8846.308088,"remaining_time":1748.072856},
{"learn":[2.897762154],"iteration":835,"passed_time":8850.381342,"remaining_time":1736.199211},
{"learn":[2.864671571],"iteration":836,"passed_time":8854.564941,"remaining_time":1724.365693},
{"learn":[2.827045089],"iteration":837,"passed_time":8858.591891,"remaining_time":1712.520151},
{"learn":[2.816368424],"iteration":838,"passed_time":8862.870968,"remaining_time":1700.741628},
{"learn":[2.788803607],"iteration":839,"passed_time":8866.950837,"remaining_time":1688.943017},
{"learn":[2.781287361],"iteration":840,"passed_time":8871.035048,"remaining_time":1677.163582},
{"learn":[2.751023229],"iteration":841,"passed_time":8875.218403,"remaining_time":1665.421031},
{"learn":[2.722887106],"iteration":842,"passed_time":8879.455182,"remaining_time":1653.706362},
{"learn":[2.716491538],"iteration":843,"passed_time":8880.418975,"remaining_time":1641.404455},
{"learn":[2.69090196],"iteration":844,"passed_time":8884.556392,"remaining_time":1629.711527},
{"learn":[2.6548873],"iteration":845,"passed_time":8888.795931,"remaining_time":1618.055051},
{"learn":[2.61839832],"iteration":846,"passed_time":8893.052166,"remaining_time":1606.419104},
{"learn":[2.610427913],"iteration":847,"passed_time":8897.304321,"remaining_time":1594.799831},
{"learn":[2.587690163],"iteration":848,"passed_time":8901.357501,"remaining_time":1583.162524},
{"learn":[2.574761998],"iteration":849,"passed_time":8905.498333,"remaining_time":1571.558529},
{"learn":[2.561601264],"iteration":850,"passed_time":8909.549568,"remaining_time":1559.956387},
{"learn":[2.526100574],"iteration":851,"passed_time":8913.803395,"remaining_time":1548.407163},
{"learn":[2.494020056],"iteration":852,"passed_time":8917.944473,"remaining_time":1536.855613},
{"learn":[2.48863823],"iteration":853,"passed_time":8922.246683,"remaining_time":1525.348965},
{"learn":[2.482880302],"iteration":854,"passed_time":8926.883357,"remaining_time":1513.915891},
{"learn":[2.464193164],"iteration":855,"passed_time":8931.117969,"remaining_time":1502.43106},
{"learn":[2.448943819],"iteration":856,"passed_time":8935.243706,"remaining_time":1490.944982},
{"learn":[2.435202695],"iteration":857,"passed_time":8939.505934,"remaining_time":1479.498651},
{"learn":[2.40472211],"iteration":858,"passed_time":8943.713682,"remaining_time":1468.060104},
{"learn":[2.392024034],"iteration":859,"passed_time":8947.927414,"remaining_time":1456.639347},
{"learn":[2.386839506],"iteration":860,"passed_time":8952.106456,"remaining_time":1445.22973},
{"learn":[2.377155202],"iteration":861,"passed_time":8956.172448,"remaining_time":1433.818791},
{"learn":[2.361376528],"iteration":862,"passed_time":8960.272051,"remaining_time":1422.43021},
{"learn":[2.351590743],"iteration":863,"passed_time":8964.382309,"remaining_time":1411.060178},
{"learn":[2.321291758],"iteration":864,"passed_time":8968.536007,"remaining_time":1399.713712},
{"learn":[2.304191136],"iteration":865,"passed_time":8972.71035,"remaining_time":1388.387052},
{"learn":[2.300754806],"iteration":866,"passed_time":8976.851905,"remaining_time":1377.071861},
{"learn":[2.28751641],"iteration":867,"passed_time":8980.95635,"remaining_time":1365.767556},
{"learn":[2.274326862],"iteration":868,"passed_time":8985.065133,"remaining_time":1354.480475},
{"learn":[2.269150914],"iteration":869,"passed_time":8989.190863,"remaining_time":1343.212428},
{"learn":[2.245861713],"iteration":870,"passed_time":8993.22041,"remaining_time":1331.946536},
{"learn":[2.233444175],"iteration":871,"passed_time":8997.32679,"remaining_time":1320.70852},
{"learn":[2.203019661],"iteration":872,"passed_time":9001.495243,"remaining_time":1309.495871},
{"learn":[2.17193077],"iteration":873,"passed_time":9005.647352,"remaining_time":1298.296987},
{"learn":[2.164409034],"iteration":874,"passed_time":9009.895282,"remaining_time":1287.127897},
{"learn":[2.142777948],"iteration":875,"passed_time":9014.069065,"remaining_time":1275.964114},
{"learn":[2.120445065],"iteration":876,"passed_time":9018.283364,"remaining_time":1264.821954},
{"learn":[2.087182934],"iteration":877,"passed_time":9022.471392,"remaining_time":1253.691925},
{"learn":[2.058378428],"iteration":878,"passed_time":9026.584309,"remaining_time":1242.567351},
{"learn":[2.035119958],"iteration":879,"passed_time":9030.618675,"remaining_time":1231.448001},
{"learn":[2.02813997],"iteration":880,"passed_time":9034.7318,"remaining_time":1220.355374},
{"learn":[2.02563105],"iteration":881,"passed_time":9038.770798,"remaining_time":1209.268656},
{"learn":[2.010428276],"iteration":882,"passed_time":9042.995309,"remaining_time":1198.222482},
{"learn":[1.981885113],"iteration":883,"passed_time":9046.951591,"remaining_time":1187.156544},
{"learn":[1.96206275],"iteration":884,"passed_time":9051.153147,"remaining_time":1176.138545},
{"learn":[1.947051016],"iteration":885,"passed_time":9055.436036,"remaining_time":1165.146397},
{"learn":[1.935601541],"iteration":886,"passed_time":9059.550537,"remaining_time":1154.147926},
{"learn":[1.913366421],"iteration":887,"passed_time":9063.79638,"remaining_time":1143.181525},
{"learn":[1.898411419],"iteration":888,"passed_time":9067.88391,"remaining_time":1132.210477},
{"learn":[1.884033998],"iteration":889,"passed_time":9072.024806,"remaining_time":1121.261493},
{"learn":[1.869071854],"iteration":890,"passed_time":9076.194727,"remaining_time":1110.331341},
{"learn":[1.856805426],"iteration":891,"passed_time":9080.229139,"remaining_time":1099.399941},
{"learn":[1.832791003],"iteration":892,"passed_time":9084.427551,"remaining_time":1088.503637},
{"learn":[1.828787098],"iteration":893,"passed_time":9088.52408,"remaining_time":1077.610238},
{"learn":[1.822226162],"iteration":894,"passed_time":9092.596708,"remaining_time":1066.729223},
{"learn":[1.80442121],"iteration":895,"passed_time":9096.770543,"remaining_time":1055.875152},
{"learn":[1.790581732],"iteration":896,"passed_time":9100.983682,"remaining_time":1045.04049},
{"learn":[1.787031302],"iteration":897,"passed_time":9105.327588,"remaining_time":1034.235428},
{"learn":[1.780140626],"iteration":898,"passed_time":9109.48745,"remaining_time":1023.424063},
{"learn":[1.765316536],"iteration":899,"passed_time":9113.881148,"remaining_time":1012.653461},
{"learn":[1.757627749],"iteration":900,"passed_time":9118.152084,"remaining_time":1001.883525},
{"learn":[1.752572215],"iteration":901,"passed_time":9118.609287,"remaining_time":990.7136476},
{"learn":[1.725876617],"iteration":902,"passed_time":9122.932385,"remaining_time":979.98277},
{"learn":[1.718864345],"iteration":903,"passed_time":9127.208763,"remaining_time":969.2611076},
{"learn":[1.712483876],"iteration":904,"passed_time":9131.439028,"remaining_time":958.5488483},
{"learn":[1.695046178],"iteration":905,"passed_time":9135.843797,"remaining_time":947.8690032},
{"learn":[1.68927476],"iteration":906,"passed_time":9140.233005,"remaining_time":937.2013996},
{"learn":[1.667487485],"iteration":907,"passed_time":9144.650524,"remaining_time":926.5504936},
{"learn":[1.651773687],"iteration":908,"passed_time":9149.132442,"remaining_time":915.9197494},
{"learn":[1.636462859],"iteration":909,"passed_time":9153.531046,"remaining_time":905.2942793},
{"learn":[1.631283157],"iteration":910,"passed_time":9157.928521,"remaining_time":894.6823692},
{"learn":[1.61566925],"iteration":911,"passed_time":9162.372714,"remaining_time":884.0885952},
{"learn":[1.610361852],"iteration":912,"passed_time":9163.467534,"remaining_time":873.1891298},
{"learn":[1.604958246],"iteration":913,"passed_time":9167.820322,"remaining_time":862.617667},
{"learn":[1.592234882],"iteration":914,"passed_time":9172.211055,"remaining_time":852.063322},
{"learn":[1.58080888],"iteration":915,"passed_time":9176.610676,"remaining_time":841.5232498},
{"learn":[1.566749459],"iteration":916,"passed_time":9181.062761,"remaining_time":831.0013186},
{"learn":[1.554002076],"iteration":917,"passed_time":9185.517412,"remaining_time":820.4928407},
{"learn":[1.542133977],"iteration":918,"passed_time":9189.995167,"remaining_time":809.999574},
{"learn":[1.533932923],"iteration":919,"passed_time":9194.423423,"remaining_time":799.5150803},
{"learn":[1.515314302],"iteration":920,"passed_time":9198.869851,"remaining_time":789.0452967},
{"learn":[1.498556663],"iteration":921,"passed_time":9203.30527,"remaining_time":778.5876476},
{"learn":[1.475001595],"iteration":922,"passed_time":9207.614704,"remaining_time":768.1325376},
{"learn":[1.453798388],"iteration":923,"passed_time":9211.944762,"remaining_time":757.6924263},
{"learn":[1.445444834],"iteration":924,"passed_time":9216.322728,"remaining_time":747.2694104},
{"learn":[1.430685264],"iteration":925,"passed_time":9220.667821,"remaining_time":736.8568237},
{"learn":[1.427606337],"iteration":926,"passed_time":9225.050471,"remaining_time":726.4602852},
{"learn":[1.417787731],"iteration":927,"passed_time":9229.49682,"remaining_time":716.0816498},
{"learn":[1.408466159],"iteration":928,"passed_time":9233.88867,"remaining_time":705.7116206},
{"learn":[1.398204262],"iteration":929,"passed_time":9238.402282,"remaining_time":695.3636126},
{"learn":[1.391663545],"iteration":930,"passed_time":9242.858354,"remaining_time":685.0238737},
{"learn":[1.377575762],"iteration":931,"passed_time":9247.256399,"remaining_time":674.692527},
{"learn":[1.368003404],"iteration":932,"passed_time":9251.656572,"remaining_time":664.3740518},
{"learn":[1.361144032],"iteration":933,"passed_time":9256.039606,"remaining_time":654.0670386},
{"learn":[1.353409007],"iteration":934,"passed_time":9260.369766,"remaining_time":643.7690212},
{"learn":[1.337516787],"iteration":935,"passed_time":9264.753576,"remaining_time":633.487424},
{"learn":[1.336838846],"iteration":936,"passed_time":9269.216119,"remaining_time":623.2237092},
{"learn":[1.321330694],"iteration":937,"passed_time":9273.622592,"remaining_time":612.9686575},
{"learn":[1.320547713],"iteration":938,"passed_time":9278.097276,"remaining_time":602.730494},
{"learn":[1.30452379],"iteration":939,"passed_time":9282.536207,"remaining_time":592.5023111},
{"learn":[1.29363188],"iteration":940,"passed_time":9287.110985,"remaining_time":582.2949502},
{"learn":[1.283776082],"iteration":941,"passed_time":9291.358535,"remaining_time":572.0794002},
{"learn":[1.267412265],"iteration":942,"passed_time":9295.534975,"remaining_time":561.8722095},
{"learn":[1.250982087],"iteration":943,"passed_time":9299.788077,"remaining_time":551.6823436},
{"learn":[1.235334154],"iteration":944,"passed_time":9303.914818,"remaining_time":541.4976878},
{"learn":[1.218970493],"iteration":945,"passed_time":9308.061703,"remaining_time":531.3269894},
{"learn":[1.211583846],"iteration":946,"passed_time":9312.01571,"remaining_time":521.1582182},
{"learn":[1.201414551],"iteration":947,"passed_time":9316.239645,"remaining_time":511.0173645},
{"learn":[1.196214754],"iteration":948,"passed_time":9320.532498,"remaining_time":500.8926843},
{"learn":[1.184539135],"iteration":949,"passed_time":9324.60779,"remaining_time":490.7688311},
{"learn":[1.178393658],"iteration":950,"passed_time":9328.829879,"remaining_time":480.6652619},
{"learn":[1.164581813],"iteration":951,"passed_time":9332.825354,"remaining_time":470.5626229},
{"learn":[1.150581968],"iteration":952,"passed_time":9336.796986,"remaining_time":460.4716247},
{"learn":[1.143492954],"iteration":953,"passed_time":9340.967621,"remaining_time":450.4030509},
{"learn":[1.130767944],"iteration":954,"passed_time":9345.133729,"remaining_time":440.3466155},
{"learn":[1.128755636],"iteration":955,"passed_time":9349.262021,"remaining_time":430.3007625},
{"learn":[1.119543794],"iteration":956,"passed_time":9353.257164,"remaining_time":420.2612937},
{"learn":[1.109586545],"iteration":957,"passed_time":9357.441357,"remaining_time":410.2427317},
{"learn":[1.10951828],"iteration":958,"passed_time":9357.489046,"remaining_time":400.05949},
{"learn":[1.103679494],"iteration":959,"passed_time":9361.556485,"remaining_time":390.0648536},
{"learn":[1.089574032],"iteration":960,"passed_time":9365.596843,"remaining_time":380.0814535},
{"learn":[1.078040206],"iteration":961,"passed_time":9369.886001,"remaining_time":370.120237},
{"learn":[1.072216145],"iteration":962,"passed_time":9374.002779,"remaining_time":360.1641774},
{"learn":[1.065361445],"iteration":963,"passed_time":9378.14296,"remaining_time":350.2211064},
{"learn":[1.056232646],"iteration":964,"passed_time":9382.359288,"remaining_time":340.2928239},
{"learn":[1.048135359],"iteration":965,"passed_time":9386.465769,"remaining_time":330.3725012},
{"learn":[1.038937486],"iteration":966,"passed_time":9390.771241,"remaining_time":320.4709937},
{"learn":[1.03024443],"iteration":967,"passed_time":9394.734922,"remaining_time":310.5697495},
{"learn":[1.025262357],"iteration":968,"passed_time":9399.068848,"remaining_time":300.6926051},
{"learn":[1.023730941],"iteration":969,"passed_time":9403.165747,"remaining_time":290.8195592},
{"learn":[1.009502243],"iteration":970,"passed_time":9407.550846,"remaining_time":280.9670181},
{"learn":[1.004401389],"iteration":971,"passed_time":9411.569341,"remaining_time":271.1151662},
{"learn":[0.9938778914],"iteration":972,"passed_time":9415.599924,"remaining_time":261.2756402},
{"learn":[0.9793438835],"iteration":973,"passed_time":9419.73387,"remaining_time":251.4508014},
{"learn":[0.9724284463],"iteration":974,"passed_time":9423.718625,"remaining_time":241.6338109},
{"learn":[0.9647448075],"iteration":975,"passed_time":9427.912893,"remaining_time":231.8339236},
{"learn":[0.9573452806],"iteration":976,"passed_time":9431.800888,"remaining_time":222.0383014},
{"learn":[0.9503647085],"iteration":977,"passed_time":9435.857885,"remaining_time":212.2585618},
{"learn":[0.9464715547],"iteration":978,"passed_time":9439.923592,"remaining_time":202.4907001},
{"learn":[0.9389120098],"iteration":979,"passed_time":9444.249087,"remaining_time":192.7397773},
{"learn":[0.9263344385],"iteration":980,"passed_time":9448.503827,"remaining_time":182.9985451},
{"learn":[0.9142236424],"iteration":981,"passed_time":9452.57544,"remaining_time":173.2651303},
{"learn":[0.905561332],"iteration":982,"passed_time":9457.208131,"remaining_time":163.5529382},
{"learn":[0.9016497135],"iteration":983,"passed_time":9461.308621,"remaining_time":153.8424166},
{"learn":[0.8931173766],"iteration":984,"passed_time":9465.585275,"remaining_time":144.1459686},
{"learn":[0.8917008163],"iteration":985,"passed_time":9469.520748,"remaining_time":134.4556699},
{"learn":[0.8891413721],"iteration":986,"passed_time":9473.955474,"remaining_time":124.7836081},
{"learn":[0.8860392253],"iteration":987,"passed_time":9478.307651,"remaining_time":115.1211456},
{"learn":[0.8811809943],"iteration":988,"passed_time":9482.300302,"remaining_time":105.465423},
{"learn":[0.8689549056],"iteration":989,"passed_time":9486.256231,"remaining_time":95.82077001},
{"learn":[0.8561436039],"iteration":990,"passed_time":9490.754011,"remaining_time":86.19251877},
{"learn":[0.842555098],"iteration":991,"passed_time":9494.865301,"remaining_time":76.57149436},
{"learn":[0.8392525306],"iteration":992,"passed_time":9499.223818,"remaining_time":66.96330989},
{"learn":[0.8345843092],"iteration":993,"passed_time":9503.297548,"remaining_time":57.3639691},
{"learn":[0.8239110574],"iteration":994,"passed_time":9507.680953,"remaining_time":47.77729122},
{"learn":[0.8217971753],"iteration":995,"passed_time":9511.666514,"remaining_time":38.19946391},
{"learn":[0.8151779281],"iteration":996,"passed_time":9515.998918,"remaining_time":28.63389845},
{"learn":[0.8078681955],"iteration":997,"passed_time":9520.01089,"remaining_time":19.07817814},
{"learn":[0.8071108469],"iteration":998,"passed_time":9524.342767,"remaining_time":9.533876643},
{"learn":[0.7995499573],"iteration":999,"passed_time":9528.359562,"remaining_time":0}
]}